Workbook

Sheet Dashboard
B1: Fincas de boda cerca de Ayala 71 · Madrid
B3: ="Radio "&Notas!B6&" km · "&COUNTA('Fincas 20 km'!B2:B39)&" espacios comparados · datos consultados en octubre de 2026" -> Radio 20 km · 38 espacios comparados · datos consultados en octubre de 2026
B5: ESPACIOS | E5: MÁS CERCANO | H5: MENÚ MEDIO «DESDE» | K5: CATERING LIBRE / LISTA | N5: TIEMPO MEDIO EN COCHE
B6: =COUNTA('Fincas 20 km'!B2:B39) -> 38 | E6: =INDEX('Fincas 20 km'!B2:B39,MATCH(MIN('Fincas 20 km'!F2:F39),'Fincas 20 km'!F2:F39,0)) -> El Jardín de Ventas | H6: =ROUND(AVERAGE('Fincas 20 km'!I2:I39),0) -> 123 | K6: =COUNTIF('Fincas 20 km'!O2:O39,"Posib*")+COUNTIF('Fincas 20 km'!O2:O39,"Proba*")+COUNTIF('Fincas 20 km'!O2:O39,"Lista*") -> 3 | N6: =ROUND(AVERAGE('Fincas 20 km'!AG2:AG39),0) -> 21
B8: dentro del radio | E8: =MIN('Fincas 20 km'!F2:F39)&" km en línea recta" -> 1.3 km en línea recta | H8: ="entre "&MIN('Fincas 20 km'!I2:I39)&" y "&MAX('Fincas 20 km'!I2:I39)&" € por invitado" -> entre 50 y 185 € por invitado | K8: ="de "&COUNTA('Fincas 20 km'!B2:B39)&" · el resto es propio o por consultar" -> de 38 · el resto es propio o por consultar | N8: ="estimado, sin tráfico extra" -> estimado, sin tráfico extra
B10: Precio y tiempo de llegada
B47: Aforo y tipo de catering
J60: Cómo leerlo: casi todos los espacios del radio tienen catering propio, así que el precio «desde» incluye comida. Los minutos son una estimación (distancia × factor carretera ÷ velocidad, ajustables en «Notas»). Pulsa «Ver ruta y tiempo» para abrir Google Maps con el tiempo real a la hora que quieras.
J66: Instagram: no he podido verificar cuentas con seguridad, así que no he escrito ninguna de memoria. En la hoja «Fincas 20 km» (columna AI) pega el @usuario y aquí aparecerá el enlace; mientras tanto, «Buscar en Instagram» abre una búsqueda directa.
B88: Ficha rápida de cada espacio (ordenados de más cerca a más lejos)
B89: Espacio | E89: Km | F89: Min. coche | G89: Menú desde | H89: Aforo máx. | I89: Catering | L89: Nota Google | M89: Instagram | O89: Ruta en vivo | S89: Tipo de catering | T89: Nº
B90: ='Fincas 20 km'!B2 -> El Jardín de Ventas | E90: ='Fincas 20 km'!F2 -> 1.3 | F90: ='Fincas 20 km'!AG2 -> 3 | G90: =IF(ISNUMBER('Fincas 20 km'!I2),'Fincas 20 km'!I2,0) -> 76 | H90: =IF(ISNUMBER('Fincas 20 km'!L2),'Fincas 20 km'!L2,0) -> 0 | I90: =IF(LEFT('Fincas 20 km'!O2,2)="No","Propio / exclusivo",IF(OR(LEFT('Fincas 20 km'!O2,5)="Posib",LEFT('Fincas 20 km'!O2,5)="Proba",LEFT('Fincas 20 km'!O2,5)="Lista",LEFT('Fincas 20 km'!O2,2)="Sí"),"Libre o lista","Por consultar")) -> Propio / exclusivo | L90: =IF(ISNUMBER('Fincas 20 km'!Y2),'Fincas 20 km'!Y2,"—") -> 4.7 | M90: ='Fincas 20 km'!AJ2 -> Buscar en Instagram | O90: ='Fincas 20 km'!AH2 -> Ver ruta y tiempo | S90: Propio / exclusivo | T90: =COUNTIF($I$90:$I$127,S90) -> 31
B91: ='Fincas 20 km'!B3 -> Real Fábrica de Tapices & El Puchero de Plata | E91: ='Fincas 20 km'!F3 -> 2.4 | F91: ='Fincas 20 km'!AG3 -> 5 | G91: =IF(ISNUMBER('Fincas 20 km'!I3),'Fincas 20 km'!I3,0) -> 138 | H91: =IF(ISNUMBER('Fincas 20 km'!L3),'Fincas 20 km'!L3,0) -> 450 | I91: =IF(LEFT('Fincas 20 km'!O3,2)="No","Propio / exclusivo",IF(OR(LEFT('Fincas 20 km'!O3,5)="Posib",LEFT('Fincas 20 km'!O3,5)="Proba",LEFT('Fincas 20 km'!O3,5)="Lista",LEFT('Fincas 20 km'!O3,2)="Sí"),"Libre o lista","Por consultar")) -> Propio / exclusivo | L91: =IF(ISNUMBER('Fincas 20 km'!Y3),'Fincas 20 km'!Y3,"—") -> — | M91: ='Fincas 20 km'!AJ3 -> Buscar en Instagram | O91: ='Fincas 20 km'!AH3 -> Ver ruta y tiempo | S91: Libre o lista | T91: =COUNTIF($I$90:$I$127,S91) -> 3
B92: ='Fincas 20 km'!B4 -> La Quinta by Madrid Catering | E92: ='Fincas 20 km'!F4 -> 3.9 | F92: ='Fincas 20 km'!AG4 -> 8 | G92: =IF(ISNUMBER('Fincas 20 km'!I4),'Fincas 20 km'!I4,0) -> 0 | H92: =IF(ISNUMBER('Fincas 20 km'!L4),'Fincas 20 km'!L4,0) -> 165 | I92: =IF(LEFT('Fincas 20 km'!O4,2)="No","Propio / exclusivo",IF(OR(LEFT('Fincas 20 km'!O4,5)="Posib",LEFT('Fincas 20 km'!O4,5)="Proba",LEFT('Fincas 20 km'!O4,5)="Lista",LEFT('Fincas 20 km'!O4,2)="Sí"),"Libre o lista","Por consultar")) -> Propio / exclusivo | L92: =IF(ISNUMBER('Fincas 20 km'!Y4),'Fincas 20 km'!Y4,"—") -> 4.5 | M92: ='Fincas 20 km'!AJ4 -> Buscar en Instagram | O92: ='Fincas 20 km'!AH4 -> Ver ruta y tiempo | S92: Por consultar | T92: =COUNTIF($I$90:$I$127,S92) -> 4
B93: ='Fincas 20 km'!B5 -> Quinta de los Molinos by Elba | E93: ='Fincas 20 km'!F5 -> 4 | F93: ='Fincas 20 km'!AG5 -> 8 | G93: =IF(ISNUMBER('Fincas 20 km'!I5),'Fincas 20 km'!I5,0) -> 138 | H93: =IF(ISNUMBER('Fincas 20 km'!L5),'Fincas 20 km'!L5,0) -> 0 | I93: =IF(LEFT('Fincas 20 km'!O5,2)="No","Propio / exclusivo",IF(OR(LEFT('Fincas 20 km'!O5,5)="Posib",LEFT('Fincas 20 km'!O5,5)="Proba",LEFT('Fincas 20 km'!O5,5)="Lista",LEFT('Fincas 20 km'!O5,2)="Sí"),"Libre o lista","Por consultar")) -> Propio / exclusivo | L93: =IF(ISNUMBER('Fincas 20 km'!Y5),'Fincas 20 km'!Y5,"—") -> 4.4 | M93: ='Fincas 20 km'!AJ5 -> Buscar en Instagram | O93: ='Fincas 20 km'!AH5 -> Ver ruta y tiempo
B94: ='Fincas 20 km'!B6 -> Palacete / Complejo Duques de Pastrana | E94: ='Fincas 20 km'!F6 -> 4.4 | F94: ='Fincas 20 km'!AG6 -> 9 | G94: =IF(ISNUMBER('Fincas 20 km'!I6),'Fincas 20 km'!I6,0) -> 0 | H94: =IF(ISNUMBER('Fincas 20 km'!L6),'Fincas 20 km'!L6,0) -> 740 | I94: =IF(LEFT('Fincas 20 km'!O6,2)="No","Propio / exclusivo",IF(OR(LEFT('Fincas 20 km'!O6,5)="Posib",LEFT('Fincas 20 km'!O6,5)="Proba",LEFT('Fincas 20 km'!O6,5)="Lista",LEFT('Fincas 20 km'!O6,2)="Sí"),"Libre o lista","Por consultar")) -> Propio / exclusivo | L94: =IF(ISNUMBER('Fincas 20 km'!Y6),'Fincas 20 km'!Y6,"—") -> 4.4 | M94: ='Fincas 20 km'!AJ6 -> Buscar en Instagram | O94: ='Fincas 20 km'!AH6 -> Ver ruta y tiempo
B95: ='Fincas 20 km'!B7 -> Café de Oriente Museo del Traje | E95: ='Fincas 20 km'!F7 -> 4.7 | F95: ='Fincas 20 km'!AG7 -> 9 | G95: =IF(ISNUMBER('Fincas 20 km'!I7),'Fincas 20 km'!I7,0) -> 140 | H95: =IF(ISNUMBER('Fincas 20 km'!L7),'Fincas 20 km'!L7,0) -> 700 | I95: =IF(LEFT('Fincas 20 km'!O7,2)="No","Propio / exclusivo",IF(OR(LEFT('Fincas 20 km'!O7,5)="Posib",LEFT('Fincas 20 km'!O7,5)="Proba",LEFT('Fincas 20 km'!O7,5)="Lista",LEFT('Fincas 20 km'!O7,2)="Sí"),"Libre o lista","Por consultar")) -> Propio / exclusivo | L95: =IF(ISNUMBER('Fincas 20 km'!Y7),'Fincas 20 km'!Y7,"—") -> 4.2 | M95: ='Fincas 20 km'!AJ7 -> Buscar en Instagram | O95: ='Fincas 20 km'!AH7 -> Ver ruta y tiempo
B96: ='Fincas 20 km'!B8 -> Casa de Burgos | E96: ='Fincas 20 km'!F8 -> 4.9 | F96: ='Fincas 20 km'!AG8 -> 10 | G96: =IF(ISNUMBER('Fincas 20 km'!I8),'Fincas 20 km'!I8,0) -> 100 | H96: =IF(ISNUMBER('Fincas 20 km'!L8),'Fincas 20 km'!L8,0) -> 350 | I96: =IF(LEFT('Fincas 20 km'!O8,2)="No","Propio / exclusivo",IF(OR(LEFT('Fincas 20 km'!O8,5)="Posib",LEFT('Fincas 20 km'!O8,5)="Proba",LEFT('Fincas 20 km'!O8,5)="Lista",LEFT('Fincas 20 km'!O8,2)="Sí"),"Libre o lista","Por consultar")) -> Propio / exclusivo | L96: =IF(ISNUMBER('Fincas 20 km'!Y8),'Fincas 20 km'!Y8,"—") -> 4.5 | M96: ='Fincas 20 km'!AJ8 -> Buscar en Instagram | O96: ='Fincas 20 km'!AH8 -> Ver ruta y tiempo
B97: ='Fincas 20 km'!B9 -> La Masía de José Luis | E97: ='Fincas 20 km'!F9 -> 4.9 | F97: ='Fincas 20 km'!AG9 -> 10 | G97: =IF(ISNUMBER('Fincas 20 km'!I9),'Fincas 20 km'!I9,0) -> 140 | H97: =IF(ISNUMBER('Fincas 20 km'!L9),'Fincas 20 km'!L9,0) -> 440 | I97: =IF(LEFT('Fincas 20 km'!O9,2)="No","Propio / exclusivo",IF(OR(LEFT('Fincas 20 km'!O9,5)="Posib",LEFT('Fincas 20 km'!O9,5)="Proba",LEFT('Fincas 20 km'!O9,5)="Lista",LEFT('Fincas 20 km'!O9,2)="Sí"),"Libre o lista","Por consultar")) -> Propio / exclusivo | L97: =IF(ISNUMBER('Fincas 20 km'!Y9),'Fincas 20 km'!Y9,"—") -> 4.5 | M97: ='Fincas 20 km'!AJ9 -> Buscar en Instagram | O97: ='Fincas 20 km'!AH9 -> Ver ruta y tiempo
B98: ='Fincas 20 km'!B10 -> Club de Campo Villa de Madrid | E98: ='Fincas 20 km'!F10 -> 5.8 | F98: ='Fincas 20 km'!AG10 -> 11 | G98: =IF(ISNUMBER('Fincas 20 km'!I10),'Fincas 20 km'!I10,0) -> 0 | H98: =IF(ISNUMBER('Fincas 20 km'!L10),'Fincas 20 km'!L10,0) -> 0 | I98: =IF(LEFT('Fincas 20 km'!O10,2)="No","Propio / exclusivo",IF(OR(LEFT('Fincas 20 km'!O10,5)="Posib",LEFT('Fincas 20 km'!O10,5)="Proba",LEFT('Fincas 20 km'!O10,5)="Lista",LEFT('Fincas 20 km'!O10,2)="Sí"),"Libre o lista","Por consultar")) -> Propio / exclusivo | L98: =IF(ISNUMBER('Fincas 20 km'!Y10),'Fincas 20 km'!Y10,"—") -> 4.3 | M98: ='Fincas 20 km'!AJ10 -> Buscar en Instagram | O98: ='Fincas 20 km'!AH10 -> Ver ruta y tiempo
B99: ='Fincas 20 km'!B11 -> Mirador del Olivar | E99: ='Fincas 20 km'!F11 -> 7.2 | F99: ='Fincas 20 km'!AG11 -> 14 | G99: =IF(ISNUMBER('Fincas 20 km'!I11),'Fincas 20 km'!I11,0) -> 99 | H99: =IF(ISNUMBER('Fincas 20 km'!L11),'Fincas 20 km'!L11,0) -> 520 | I99: =IF(LEFT('Fincas 20 km'!O11,2)="No","Propio / exclusivo",IF(OR(LEFT('Fincas 20 km'!O11,5)="Posib",LEFT('Fincas 20 km'!O11,5)="Proba",LEFT('Fincas 20 km'!O11,5)="Lista",LEFT('Fincas 20 km'!O11,2)="Sí"),"Libre o lista","Por consultar")) -> Propio / exclusivo | L99: =IF(ISNUMBER('Fincas 20 km'!Y11),'Fincas 20 km'!Y11,"—") -> 4.1 | M99: ='Fincas 20 km'!AJ11 -> Buscar en Instagram | O99: ='Fincas 20 km'!AH11 -> Ver ruta y tiempo
B100: ='Fincas 20 km'!B12 -> Club de Tiro de Madrid | E100: ='Fincas 20 km'!F12 -> 8.9 | F100: ='Fincas 20 km'!AG12 -> 17 | G100: =IF(ISNUMBER('Fincas 20 km'!I12),'Fincas 20 km'!I12,0) -> 130 | H100: =IF(ISNUMBER('Fincas 20 km'!L12),'Fincas 20 km'!L12,0) -> 600 | I100: =IF(LEFT('Fincas 20 km'!O12,2)="No","Propio / exclusivo",IF(OR(LEFT('Fincas 20 km'!O12,5)="Posib",LEFT('Fincas 20 km'!O12,5)="Proba",LEFT('Fincas 20 km'!O12,5)="Lista",LEFT('Fincas 20 km'!O12,2)="Sí"),"Libre o lista","Por consultar")) -> Propio / exclusivo | L100: =IF(ISNUMBER('Fincas 20 km'!Y12),'Fincas 20 km'!Y12,"—") -> 4.3 | M100: ='Fincas 20 km'!AJ12 -> Buscar en Instagram | O100: ='Fincas 20 km'!AH12 -> Ver ruta y tiempo
B101: ='Fincas 20 km'!B13 -> Fuentearcos | E101: ='Fincas 20 km'!F13 -> 9.5 | F101: ='Fincas 20 km'!AG13 -> 19 | G101: =IF(ISNUMBER('Fincas 20 km'!I13),'Fincas 20 km'!I13,0) -> 120 | H101: =IF(ISNUMBER('Fincas 20 km'!L13),'Fincas 20 km'!L13,0) -> 350 | I101: =IF(LEFT('Fincas 20 km'!O13,2)="No","Propio / exclusivo",IF(OR(LEFT('Fincas 20 km'!O13,5)="Posib",LEFT('Fincas 20 km'!O13,5)="Proba",LEFT('Fincas 20 km'!O13,5)="Lista",LEFT('Fincas 20 km'!O13,2)="Sí"),"Libre o lista","Por consultar")) -> Propio / exclusivo | L101: =IF(ISNUMBER('Fincas 20 km'!Y13),'Fincas 20 km'!Y13,"—") -> 4.4 | M101: ='Fincas 20 km'!AJ13 -> Buscar en Instagram | O101: ='Fincas 20 km'!AH13 -> Ver ruta y tiempo
B102: ='Fincas 20 km'!B14 -> Finca Solimpar | E102: ='Fincas 20 km'!F14 -> 9.7 | F102: ='Fincas 20 km'!AG14 -> 19 | G102: =IF(ISNUMBER('Fincas 20 km'!I14),'Fincas 20 km'!I14,0) -> 90 | H102: =IF(ISNUMBER('Fincas 20 km'!L14),'Fincas 20 km'!L14,0) -> 300 | I102: =IF(LEFT('Fincas 20 km'!O14,2)="No","Propio / exclusivo",IF(OR(LEFT('Fincas 20 km'!O14,5)="Posib",LEFT('Fincas 20 km'!O14,5)="Proba",LEFT('Fincas 20 km'!O14,5)="Lista",LEFT('Fincas 20 km'!O14,2)="Sí"),"Libre o lista","Por consultar")) -> Propio / exclusivo | L102: =IF(ISNUMBER('Fincas 20 km'!Y14),'Fincas 20 km'!Y14,"—") -> 4.4 | M102: ='Fincas 20 km'!AJ14 -> Buscar en Instagram | O102: ='Fincas 20 km'!AH14 -> Ver ruta y tiempo
B103: ='Fincas 20 km'!B15 -> El Jardín de Somontes (Eventos Somontes) | E103: ='Fincas 20 km'!F15 -> 9.7 | F103: ='Fincas 20 km'!AG15 -> 19 | G103: =IF(ISNUMBER('Fincas 20 km'!I15),'Fincas 20 km'!I15,0) -> 0 | H103: =IF(ISNUMBER('Fincas 20 km'!L15),'Fincas 20 km'!L15,0) -> 400 | I103: =IF(LEFT('Fincas 20 km'!O15,2)="No","Propio / exclusivo",IF(OR(LEFT('Fincas 20 km'!O15,5)="Posib",LEFT('Fincas 20 km'!O15,5)="Proba",LEFT('Fincas 20 km'!O15,5)="Lista",LEFT('Fincas 20 km'!O15,2)="Sí"),"Libre o lista","Por consultar")) -> Libre o lista | L103: =IF(ISNUMBER('Fincas 20 km'!Y15),'Fincas 20 km'!Y15,"—") -> 4.5 | M103: ='Fincas 20 km'!AJ15 -> Buscar en Instagram | O103: ='Fincas 20 km'!AH15 -> Ver ruta y tiempo
B104: ='Fincas 20 km'!B16 -> La Casa de Mónico | E104: ='Fincas 20 km'!F16 -> 9.8 | F104: ='Fincas 20 km'!AG16 -> 19 | G104: =IF(ISNUMBER('Fincas 20 km'!I16),'Fincas 20 km'!I16,0) -> 185 | H104: =IF(ISNUMBER('Fincas 20 km'!L16),'Fincas 20 km'!L16,0) -> 600 | I104: =IF(LEFT('Fincas 20 km'!O16,2)="No","Propio / exclusivo",IF(OR(LEFT('Fincas 20 km'!O16,5)="Posib",LEFT('Fincas 20 km'!O16,5)="Proba",LEFT('Fincas 20 km'!O16,5)="Lista",LEFT('Fincas 20 km'!O16,2)="Sí"),"Libre o lista","Por consultar")) -> Propio / exclusivo | L104: =IF(ISNUMBER('Fincas 20 km'!Y16),'Fincas 20 km'!Y16,"—") -> 4.5 | M104: ='Fincas 20 km'!AJ16 -> Buscar en Instagram | O104: ='Fincas 20 km'!AH16 -> Ver ruta y tiempo
... B127: ='Fincas 20 km'!B39 -> Señorío de Ajuria | E127: ='Fincas 20 km'!F39 -> 19.2 | F127: ='Fincas 20 km'!AG39 -> 37 | G127: =IF(ISNUMBER('Fincas 20 km'!I39),'Fincas 20 km'!I39,0) -> 90 | H127: =IF(ISNUMBER('Fincas 20 km'!L39),'Fincas 20 km'!L39,0) -> 300 | I127: =IF(LEFT('Fincas 20 km'!O39,2)="No","Propio / exclusivo",IF(OR(LEFT('Fincas 20 km'!O39,5)="Posib",LEFT('Fincas 20 km'!O39,5)="Proba",LEFT('Fincas 20 km'!O39,5)="Lista",LEFT('Fincas 20 km'!O39,2)="Sí"),"Libre o lista","Por consultar")) -> Propio / exclusivo | L127: =IF(ISNUMBER('Fincas 20 km'!Y39),'Fincas 20 km'!Y39,"—") -> 4 | M127: ='Fincas 20 km'!AJ39 -> Buscar en Instagram | O127: ='Fincas 20 km'!AH39 -> Ver ruta y tiempo

Sheet Ficha interactiva
B1: Ficha interactiva de finca
B3: Elige una finca en la celda amarilla y cambia los parámetros: todo se recalcula solo. | P3: Datos auxiliares (no tocar)
P4: Precio publicado | Q4: =IF(INDEX('Fincas 20 km'!$I$2:$I$39,$K$5)="","",INDEX('Fincas 20 km'!$I$2:$I$39,$K$5)) -> 76
B5: FINCA ▸ | D5: El Jardín de Ventas | J5: nº en lista | K5: =MATCH($D$5,'Fincas 20 km'!$B$2:$B$39,0) -> 1 | P5: Aforo mín. | Q5: =IF(INDEX('Fincas 20 km'!$K$2:$K$39,$K$5)="","",INDEX('Fincas 20 km'!$K$2:$K$39,$K$5))
P6: Aforo máx. | Q6: =IF(INDEX('Fincas 20 km'!$L$2:$L$39,$K$5)="","",INDEX('Fincas 20 km'!$L$2:$L$39,$K$5))
B7: Tus parámetros (celdas amarillas) | P7: Km en línea recta | Q7: =INDEX('Fincas 20 km'!$F$2:$F$39,$K$5) -> 1.3
B8: Invitados | F8: 120 | H8: IVA (%) | L8: 10 | P8: Precio usado | Q8: =IF(ISNUMBER($F$9),$F$9,$Q$4) -> 76
B9: Precio por invitado (€) · vacío = el publicado | H9: Factor carretera / línea recta | L9: 1.3 | P9: Invitados | Q9: =$F$8 -> 120
B10: Extras por invitado (€) · barra libre extra, recena… | F10: 0 | H10: Velocidad media (km/h) | L10: 40 | P10: Minutos elegida | Q10: =ROUND($Q$7*$L$9/$L$10*60,0) -> 3
B11: Costes fijos (€) · alquiler, DJ, flores… | F11: 0 | P11: Menú elegida (usado) | Q11: =IF(ISNUMBER($Q$8),$Q$8,NA()) -> 76
P12: Finca | Q12: Minutos | R12: Menú desde | T12: Total (otras) | U12: Total (elegida)
B13: COSTE TOTAL ESTIMADO | E13: POR INVITADO | H13: EN COCHE (ESTIM.) | K13: DISTANCIA EN LÍNEA RECTA | P13: ='Fincas 20 km'!B2 -> El Jardín de Ventas | Q13: =ROUND('Fincas 20 km'!F2*$L$9/$L$10*60,0) -> 3 | R13: =IF('Fincas 20 km'!I2="",NA(),'Fincas 20 km'!I2) -> 76 | T13: =IF($P13=$D$5,0,IF(ISNUMBER(R13),(IF(AND($P13=$D$5,ISNUMBER($F$9)),$F$9,R13)*$F$8+$F$8*$F$10+$F$11)*(1+$L$8/100),0)) -> 0 | U13: =IF($P13=$D$5,IF(ISNUMBER(R13),(IF(AND($P13=$D$5,ISNUMBER($F$9)),$F$9,R13)*$F$8+$F$8*$F$10+$F$11)*(1+$L$8/100),0),0) -> 10032
B14: =IF(ISNUMBER($F$22),$F$22,"—") -> 10032 | E14: =IF(ISNUMBER($F$22),$F$22/$F$8,"—") -> 83.6 | H14: =ROUND($Q$7*$L$9/$L$10*60,0) -> 3 | K14: =$Q$7 -> 1.3 | P14: ='Fincas 20 km'!B3 -> Real Fábrica de Tapices & El Puchero de Plata | Q14: =ROUND('Fincas 20 km'!F3*$L$9/$L$10*60,0) -> 5 | R14: =IF('Fincas 20 km'!I3="",NA(),'Fincas 20 km'!I3) -> 138 | T14: =IF($P14=$D$5,0,IF(ISNUMBER(R14),(IF(AND($P14=$D$5,ISNUMBER($F$9)),$F$9,R14)*$F$8+$F$8*$F$10+$F$11)*(1+$L$8/100),0)) -> 18216 | U14: =IF($P14=$D$5,IF(ISNUMBER(R14),(IF(AND($P14=$D$5,ISNUMBER($F$9)),$F$9,R14)*$F$8+$F$8*$F$10+$F$11)*(1+$L$8/100),0),0) -> 0
P15: ='Fincas 20 km'!B4 -> La Quinta by Madrid Catering | Q15: =ROUND('Fincas 20 km'!F4*$L$9/$L$10*60,0) -> 8 | R15: =IF('Fincas 20 km'!I4="",NA(),'Fincas 20 km'!I4) -> #N/A | T15: =IF($P15=$D$5,0,IF(ISNUMBER(R15),(IF(AND($P15=$D$5,ISNUMBER($F$9)),$F$9,R15)*$F$8+$F$8*$F$10+$F$11)*(1+$L$8/100),0)) -> 0 | U15: =IF($P15=$D$5,IF(ISNUMBER(R15),(IF(AND($P15=$D$5,ISNUMBER($F$9)),$F$9,R15)*$F$8+$F$8*$F$10+$F$11)*(1+$L$8/100),0),0) -> 0
B16: =IF(ISNUMBER($F$22),$F$8&" invitados × "&TEXT($Q$8,"#,##0")&" € + extras, fijos e IVA","Sin precio publicado: escribe el tuyo arriba") -> 120 invitados × 76 € + extras, fijos e IVA | E16: ="con IVA del "&$L$8&" %" -> con IVA del 10 % | H16: ="a "&$L$10&" km/h, factor "&TEXT($L$9,"0.0") -> a 40 km/h, factor 1.3 | K16: mismo dato que el Excel | P16: ='Fincas 20 km'!B5 -> Quinta de los Molinos by Elba | Q16: =ROUND('Fincas 20 km'!F5*$L$9/$L$10*60,0) -> 8 | R16: =IF('Fincas 20 km'!I5="",NA(),'Fincas 20 km'!I5) -> 138 | T16: =IF($P16=$D$5,0,IF(ISNUMBER(R16),(IF(AND($P16=$D$5,ISNUMBER($F$9)),$F$9,R16)*$F$8+$F$8*$F$10+$F$11)*(1+$L$8/100),0)) -> 18216 | U16: =IF($P16=$D$5,IF(ISNUMBER(R16),(IF(AND($P16=$D$5,ISNUMBER($F$9)),$F$9,R16)*$F$8+$F$8*$F$10+$F$11)*(1+$L$8/100),0),0) -> 0
P17: ='Fincas 20 km'!B6 -> Palacete / Complejo Duques de Pastrana | Q17: =ROUND('Fincas 20 km'!F6*$L$9/$L$10*60,0) -> 9 | R17: =IF('Fincas 20 km'!I6="",NA(),'Fincas 20 km'!I6) -> #N/A | T17: =IF($P17=$D$5,0,IF(ISNUMBER(R17),(IF(AND($P17=$D$5,ISNUMBER($F$9)),$F$9,R17)*$F$8+$F$8*$F$10+$F$11)*(1+$L$8/100),0)) -> 0 | U17: =IF($P17=$D$5,IF(ISNUMBER(R17),(IF(AND($P17=$D$5,ISNUMBER($F$9)),$F$9,R17)*$F$8+$F$8*$F$10+$F$11)*(1+$L$8/100),0),0) -> 0
B18: Desglose del coste | P18: ='Fincas 20 km'!B7 -> Café de Oriente Museo del Traje | Q18: =ROUND('Fincas 20 km'!F7*$L$9/$L$10*60,0) -> 9 | R18: =IF('Fincas 20 km'!I7="",NA(),'Fincas 20 km'!I7) -> 140 | T18: =IF($P18=$D$5,0,IF(ISNUMBER(R18),(IF(AND($P18=$D$5,ISNUMBER($F$9)),$F$9,R18)*$F$8+$F$8*$F$10+$F$11)*(1+$L$8/100),0)) -> 18480 | U18: =IF($P18=$D$5,IF(ISNUMBER(R18),(IF(AND($P18=$D$5,ISNUMBER($F$9)),$F$9,R18)*$F$8+$F$8*$F$10+$F$11)*(1+$L$8/100),0),0) -> 0
B19: Menú (invitados × precio) | F19: =IF(ISNUMBER($Q$8),$F$8*$Q$8,"") -> 9120 | G19: =IF(ISNUMBER($F$22),F19/$F$22,"") -> 0.90909091 | P19: ='Fincas 20 km'!B8 -> Casa de Burgos | Q19: =ROUND('Fincas 20 km'!F8*$L$9/$L$10*60,0) -> 10 | R19: =IF('Fincas 20 km'!I8="",NA(),'Fincas 20 km'!I8) -> 100 | T19: =IF($P19=$D$5,0,IF(ISNUMBER(R19),(IF(AND($P19=$D$5,ISNUMBER($F$9)),$F$9,R19)*$F$8+$F$8*$F$10+$F$11)*(1+$L$8/100),0)) -> 13200 | U19: =IF($P19=$D$5,IF(ISNUMBER(R19),(IF(AND($P19=$D$5,ISNUMBER($F$9)),$F$9,R19)*$F$8+$F$8*$F$10+$F$11)*(1+$L$8/100),0),0) -> 0
B20: Extras | F20: =IF(ISNUMBER($Q$8),$F$8*$F$10,"") -> 0 | G20: =IF(ISNUMBER($F$22),F20/$F$22,"") -> 0 | P20: ='Fincas 20 km'!B9 -> La Masía de José Luis | Q20: =ROUND('Fincas 20 km'!F9*$L$9/$L$10*60,0) -> 10 | R20: =IF('Fincas 20 km'!I9="",NA(),'Fincas 20 km'!I9) -> 140 | T20: =IF($P20=$D$5,0,IF(ISNUMBER(R20),(IF(AND($P20=$D$5,ISNUMBER($F$9)),$F$9,R20)*$F$8+$F$8*$F$10+$F$11)*(1+$L$8/100),0)) -> 18480 | U20: =IF($P20=$D$5,IF(ISNUMBER(R20),(IF(AND($P20=$D$5,ISNUMBER($F$9)),$F$9,R20)*$F$8+$F$8*$F$10+$F$11)*(1+$L$8/100),0),0) -> 0
B21: Costes fijos | F21: =IF(ISNUMBER($Q$8),$F$11,"") -> 0 | G21: =IF(ISNUMBER($F$22),F21/$F$22,"") -> 0 | P21: ='Fincas 20 km'!B10 -> Club de Campo Villa de Madrid | Q21: =ROUND('Fincas 20 km'!F10*$L$9/$L$10*60,0) -> 11 | R21: =IF('Fincas 20 km'!I10="",NA(),'Fincas 20 km'!I10) -> #N/A | T21: =IF($P21=$D$5,0,IF(ISNUMBER(R21),(IF(AND($P21=$D$5,ISNUMBER($F$9)),$F$9,R21)*$F$8+$F$8*$F$10+$F$11)*(1+$L$8/100),0)) -> 0 | U21: =IF($P21=$D$5,IF(ISNUMBER(R21),(IF(AND($P21=$D$5,ISNUMBER($F$9)),$F$9,R21)*$F$8+$F$8*$F$10+$F$11)*(1+$L$8/100),0),0) -> 0
B22: TOTAL (con IVA) | F22: =IF(ISNUMBER($Q$8),SUM($F$19:$F$21)+$F$23,"") -> 10032 | G22: =IF(ISNUMBER($F$22),F22/$F$22,"") -> 1 | P22: ='Fincas 20 km'!B11 -> Mirador del Olivar | Q22: =ROUND('Fincas 20 km'!F11*$L$9/$L$10*60,0) -> 14 | R22: =IF('Fincas 20 km'!I11="",NA(),'Fincas 20 km'!I11) -> 99 | T22: =IF($P22=$D$5,0,IF(ISNUMBER(R22),(IF(AND($P22=$D$5,ISNUMBER($F$9)),$F$9,R22)*$F$8+$F$8*$F$10+$F$11)*(1+$L$8/100),0)) -> 13068 | U22: =IF($P22=$D$5,IF(ISNUMBER(R22),(IF(AND($P22=$D$5,ISNUMBER($F$9)),$F$9,R22)*$F$8+$F$8*$F$10+$F$11)*(1+$L$8/100),0),0) -> 0
B23: de los cuales, IVA | F23: =IF(ISNUMBER($Q$8),SUM($F$19:$F$21)*$L$8/100,"") -> 912 | G23: =IF(ISNUMBER($F$22),F23/$F$22,"") -> 0.090909091 | P23: ='Fincas 20 km'!B12 -> Club de Tiro de Madrid | Q23: =ROUND('Fincas 20 km'!F12*$L$9/$L$10*60,0) -> 17 | R23: =IF('Fincas 20 km'!I12="",NA(),'Fincas 20 km'!I12) -> 130 | T23: =IF($P23=$D$5,0,IF(ISNUMBER(R23),(IF(AND($P23=$D$5,ISNUMBER($F$9)),$F$9,R23)*$F$8+$F$8*$F$10+$F$11)*(1+$L$8/100),0)) -> 17160 | U23: =IF($P23=$D$5,IF(ISNUMBER(R23),(IF(AND($P23=$D$5,ISNUMBER($F$9)),$F$9,R23)*$F$8+$F$8*$F$10+$F$11)*(1+$L$8/100),0),0) -> 0
P24: ='Fincas 20 km'!B13 -> Fuentearcos | Q24: =ROUND('Fincas 20 km'!F13*$L$9/$L$10*60,0) -> 19 | R24: =IF('Fincas 20 km'!I13="",NA(),'Fincas 20 km'!I13) -> 120 | T24: =IF($P24=$D$5,0,IF(ISNUMBER(R24),(IF(AND($P24=$D$5,ISNUMBER($F$9)),$F$9,R24)*$F$8+$F$8*$F$10+$F$11)*(1+$L$8/100),0)) -> 15840 | U24: =IF($P24=$D$5,IF(ISNUMBER(R24),(IF(AND($P24=$D$5,ISNUMBER($F$9)),$F$9,R24)*$F$8+$F$8*$F$10+$F$11)*(1+$L$8/100),0),0) -> 0
B25: =IF(NOT(ISNUMBER($Q$8)),"⚠ Esta finca no publica precio: escribe tu estimación en «Precio por invitado».","") | P25: ='Fincas 20 km'!B14 -> Finca Solimpar | Q25: =ROUND('Fincas 20 km'!F14*$L$9/$L$10*60,0) -> 19 | R25: =IF('Fincas 20 km'!I14="",NA(),'Fincas 20 km'!I14) -> 90 | T25: =IF($P25=$D$5,0,IF(ISNUMBER(R25),(IF(AND($P25=$D$5,ISNUMBER($F$9)),$F$9,R25)*$F$8+$F$8*$F$10+$F$11)*(1+$L$8/100),0)) -> 11880 | U25: =IF($P25=$D$5,IF(ISNUMBER(R25),(IF(AND($P25=$D$5,ISNUMBER($F$9)),$F$9,R25)*$F$8+$F$8*$F$10+$F$11)*(1+$L$8/100),0),0) -> 0
B26: =IF(AND(ISNUMBER($Q$5),$F$8<$Q$5),"⚠ Con "&$F$8&" invitados quedas por debajo del mínimo habitual ("&$Q$5&"): suelen cobrar la diferencia.","") | P26: ='Fincas 20 km'!B15 -> El Jardín de Somontes (Eventos Somontes) | Q26: =ROUND('Fincas 20 km'!F15*$L$9/$L$10*60,0) -> 19 | R26: =IF('Fincas 20 km'!I15="",NA(),'Fincas 20 km'!I15) -> #N/A | T26: =IF($P26=$D$5,0,IF(ISNUMBER(R26),(IF(AND($P26=$D$5,ISNUMBER($F$9)),$F$9,R26)*$F$8+$F$8*$F$10+$F$11)*(1+$L$8/100),0)) -> 0 | U26: =IF($P26=$D$5,IF(ISNUMBER(R26),(IF(AND($P26=$D$5,ISNUMBER($F$9)),$F$9,R26)*$F$8+$F$8*$F$10+$F$11)*(1+$L$8/100),0),0) -> 0
B27: =IF(AND(ISNUMBER($Q$6),$F$8>$Q$6),"⛔ Con "&$F$8&" invitados superas el aforo máximo publicado ("&$Q$6&").","") | P27: ='Fincas 20 km'!B16 -> La Casa de Mónico | Q27: =ROUND('Fincas 20 km'!F16*$L$9/$L$10*60,0) -> 19 | R27: =IF('Fincas 20 km'!I16="",NA(),'Fincas 20 km'!I16) -> 185 | T27: =IF($P27=$D$5,0,IF(ISNUMBER(R27),(IF(AND($P27=$D$5,ISNUMBER($F$9)),$F$9,R27)*$F$8+$F$8*$F$10+$F$11)*(1+$L$8/100),0)) -> 24420 | U27: =IF($P27=$D$5,IF(ISNUMBER(R27),(IF(AND($P27=$D$5,ISNUMBER($F$9)),$F$9,R27)*$F$8+$F$8*$F$10+$F$11)*(1+$L$8/100),0),0) -> 0
B28: =IF(AND(ISNUMBER($Q$6),$F$8<=$Q$6,OR(NOT(ISNUMBER($Q$5)),$F$8>=$Q$5)),"✓ Tus invitados caben dentro del aforo publicado.","") | P28: ='Fincas 20 km'!B17 -> Finca La Gaivota | Q28: =ROUND('Fincas 20 km'!F17*$L$9/$L$10*60,0) -> 19 | R28: =IF('Fincas 20 km'!I17="",NA(),'Fincas 20 km'!I17) -> #N/A | T28: =IF($P28=$D$5,0,IF(ISNUMBER(R28),(IF(AND($P28=$D$5,ISNUMBER($F$9)),$F$9,R28)*$F$8+$F$8*$F$10+$F$11)*(1+$L$8/100),0)) -> 0 | U28: =IF($P28=$D$5,IF(ISNUMBER(R28),(IF(AND($P28=$D$5,ISNUMBER($F$9)),$F$9,R28)*$F$8+$F$8*$F$10+$F$11)*(1+$L$8/100),0),0) -> 0
B29: =IF(ISNUMBER(SEARCH("mínim",INDEX('Fincas 20 km'!$H$2:$H$39,$K$5))),"⚠ El precio publicado menciona un mínimo de facturación: léelo completo en «Precio publicado».","") -> ⚠ El precio publicado menciona un mínimo de facturación: léelo completo en «Precio publicado». | P29: ='Fincas 20 km'!B18 -> Finca Astilbe (by Eneldo) | Q29: =ROUND('Fincas 20 km'!F18*$L$9/$L$10*60,0) -> 21 | R29: =IF('Fincas 20 km'!I18="",NA(),'Fincas 20 km'!I18) -> 145 | T29: =IF($P29=$D$5,0,IF(ISNUMBER(R29),(IF(AND($P29=$D$5,ISNUMBER($F$9)),$F$9,R29)*$F$8+$F$8*$F$10+$F$11)*(1+$L$8/100),0)) -> 19140 | U29: =IF($P29=$D$5,IF(ISNUMBER(R29),(IF(AND($P29=$D$5,ISNUMBER($F$9)),$F$9,R29)*$F$8+$F$8*$F$10+$F$11)*(1+$L$8/100),0),0) -> 0
P30: ='Fincas 20 km'!B19 -> El Mirador de Cuatrovientos (incl. Finca Las Palmeras) | Q30: =ROUND('Fincas 20 km'!F19*$L$9/$L$10*60,0) -> 21 | R30: =IF('Fincas 20 km'!I19="",NA(),'Fincas 20 km'!I19) -> 99 | T30: =IF($P30=$D$5,0,IF(ISNUMBER(R30),(IF(AND($P30=$D$5,ISNUMBER($F$9)),$F$9,R30)*$F$8+$F$8*$F$10+$F$11)*(1+$L$8/100),0)) -> 13068 | U30: =IF($P30=$D$5,IF(ISNUMBER(R30),(IF(AND($P30=$D$5,ISNUMBER($F$9)),$F$9,R30)*$F$8+$F$8*$F$10+$F$11)*(1+$L$8/100),0),0) -> 0
B31: Ficha de la finca | P31: ='Fincas 20 km'!B20 -> U-Zalacaín La Finca | Q31: =ROUND('Fincas 20 km'!F20*$L$9/$L$10*60,0) -> 21 | R31: =IF('Fincas 20 km'!I20="",NA(),'Fincas 20 km'!I20) -> 135 | T31: =IF($P31=$D$5,0,IF(ISNUMBER(R31),(IF(AND($P31=$D$5,ISNUMBER($F$9)),$F$9,R31)*$F$8+$F$8*$F$10+$F$11)*(1+$L$8/100),0)) -> 17820 | U31: =IF($P31=$D$5,IF(ISNUMBER(R31),(IF(AND($P31=$D$5,ISNUMBER($F$9)),$F$9,R31)*$F$8+$F$8*$F$10+$F$11)*(1+$L$8/100),0),0) -> 0
B32: Tipo de espacio | E32: =IFERROR(IF(INDEX('Fincas 20 km'!$C$2:$C$39,$K$5)="","No consta",INDEX('Fincas 20 km'!$C$2:$C$39,$K$5)),"—") -> Jardín del hotel NH Madrid Ventas | P32: ='Fincas 20 km'!B21 -> Finca La Muñoza (La Cococha) | Q32: =ROUND('Fincas 20 km'!F21*$L$9/$L$10*60,0) -> 21 | R32: =IF('Fincas 20 km'!I21="",NA(),'Fincas 20 km'!I21) -> 125 | T32: =IF($P32=$D$5,0,IF(ISNUMBER(R32),(IF(AND($P32=$D$5,ISNUMBER($F$9)),$F$9,R32)*$F$8+$F$8*$F$10+$F$11)*(1+$L$8/100),0)) -> 16500 | U32: =IF($P32=$D$5,IF(ISNUMBER(R32),(IF(AND($P32=$D$5,ISNUMBER($F$9)),$F$9,R32)*$F$8+$F$8*$F$10+$F$11)*(1+$L$8/100),0),0) -> 0
B33: Zona | E33: =IFERROR(IF(INDEX('Fincas 20 km'!$D$2:$D$39,$K$5)="","No consta",INDEX('Fincas 20 km'!$D$2:$D$39,$K$5)),"—") -> Madrid – Ventas (Salamanca) | P33: ='Fincas 20 km'!B22 -> Real Club La Moraleja | Q33: =ROUND('Fincas 20 km'!F22*$L$9/$L$10*60,0) -> 22 | R33: =IF('Fincas 20 km'!I22="",NA(),'Fincas 20 km'!I22) -> #N/A | T33: =IF($P33=$D$5,0,IF(ISNUMBER(R33),(IF(AND($P33=$D$5,ISNUMBER($F$9)),$F$9,R33)*$F$8+$F$8*$F$10+$F$11)*(1+$L$8/100),0)) -> 0 | U33: =IF($P33=$D$5,IF(ISNUMBER(R33),(IF(AND($P33=$D$5,ISNUMBER($F$9)),$F$9,R33)*$F$8+$F$8*$F$10+$F$11)*(1+$L$8/100),0),0) -> 0
B34: Dirección | E34: =IFERROR(IF(INDEX('Fincas 20 km'!$E$2:$E$39,$K$5)="","No consta",INDEX('Fincas 20 km'!$E$2:$E$39,$K$5)),"—") -> C/ de Biarritz 2, 28028 Madrid | P34: ='Fincas 20 km'!B23 -> Finca Petit Moraleja | Q34: =ROUND('Fincas 20 km'!F23*$L$9/$L$10*60,0) -> 24 | R34: =IF('Fincas 20 km'!I23="",NA(),'Fincas 20 km'!I23) -> #N/A | T34: =IF($P34=$D$5,0,IF(ISNUMBER(R34),(IF(AND($P34=$D$5,ISNUMBER($F$9)),$F$9,R34)*$F$8+$F$8*$F$10+$F$11)*(1+$L$8/100),0)) -> 0 | U34: =IF($P34=$D$5,IF(ISNUMBER(R34),(IF(AND($P34=$D$5,ISNUMBER($F$9)),$F$9,R34)*$F$8+$F$8*$F$10+$F$11)*(1+$L$8/100),0),0) -> 0
B35: Aforo | E35: =IFERROR(IF(INDEX('Fincas 20 km'!$M$2:$M$39,$K$5)="","No consta",INDEX('Fincas 20 km'!$M$2:$M$39,$K$5)),"—") -> No publicado | P35: ='Fincas 20 km'!B24 -> El Jardín de la Florida | Q35: =ROUND('Fincas 20 km'!F24*$L$9/$L$10*60,0) -> 25 | R35: =IF('Fincas 20 km'!I24="",NA(),'Fincas 20 km'!I24) -> #N/A | T35: =IF($P35=$D$5,0,IF(ISNUMBER(R35),(IF(AND($P35=$D$5,ISNUMBER($F$9)),$F$9,R35)*$F$8+$F$8*$F$10+$F$11)*(1+$L$8/100),0)) -> 0 | U35: =IF($P35=$D$5,IF(ISNUMBER(R35),(IF(AND($P35=$D$5,ISNUMBER($F$9)),$F$9,R35)*$F$8+$F$8*$F$10+$F$11)*(1+$L$8/100),0),0) -> 0
B36: Catering (quién lo da) | E36: =IFERROR(IF(INDEX('Fincas 20 km'!$N$2:$N$39,$K$5)="","No consta",INDEX('Fincas 20 km'!$N$2:$N$39,$K$5)),"—") -> Cocina del hotel NH Ventas | P36: ='Fincas 20 km'!B25 -> Initium (Artigot Catering) | Q36: =ROUND('Fincas 20 km'!F25*$L$9/$L$10*60,0) -> 25 | R36: =IF('Fincas 20 km'!I25="",NA(),'Fincas 20 km'!I25) -> 150 | T36: =IF($P36=$D$5,0,IF(ISNUMBER(R36),(IF(AND($P36=$D$5,ISNUMBER($F$9)),$F$9,R36)*$F$8+$F$8*$F$10+$F$11)*(1+$L$8/100),0)) -> 19800 | U36: =IF($P36=$D$5,IF(ISNUMBER(R36),(IF(AND($P36=$D$5,ISNUMBER($F$9)),$F$9,R36)*$F$8+$F$8*$F$10+$F$11)*(1+$L$8/100),0),0) -> 0
B37: ¿Catering libre? | E37: =IFERROR(IF(INDEX('Fincas 20 km'!$O$2:$O$39,$K$5)="","No consta",INDEX('Fincas 20 km'!$O$2:$O$39,$K$5)),"—") -> No (catering del hotel); tarta propia permitida | P37: ='Fincas 20 km'!B26 -> Finca El Chaparral | Q37: =ROUND('Fincas 20 km'!F26*$L$9/$L$10*60,0) -> 25 | R37: =IF('Fincas 20 km'!I26="",NA(),'Fincas 20 km'!I26) -> #N/A | T37: =IF($P37=$D$5,0,IF(ISNUMBER(R37),(IF(AND($P37=$D$5,ISNUMBER($F$9)),$F$9,R37)*$F$8+$F$8*$F$10+$F$11)*(1+$L$8/100),0)) -> 0 | U37: =IF($P37=$D$5,IF(ISNUMBER(R37),(IF(AND($P37=$D$5,ISNUMBER($F$9)),$F$9,R37)*$F$8+$F$8*$F$10+$F$11)*(1+$L$8/100),0),0) -> 0
B38: Salones y espacios | E38: =IFERROR(IF(INDEX('Fincas 20 km'!$P$2:$P$39,$K$5)="","No consta",INDEX('Fincas 20 km'!$P$2:$P$39,$K$5)),"—") -> Jardín (ceremonia civil y cóctel) + terraza reformada + salón del hotel; banquete también al aire libre | P38: ='Fincas 20 km'!B27 -> Torzares (finca La Escorzonera) | Q38: =ROUND('Fincas 20 km'!F27*$L$9/$L$10*60,0) -> 27 | R38: =IF('Fincas 20 km'!I27="",NA(),'Fincas 20 km'!I27) -> #N/A | T38: =IF($P38=$D$5,0,IF(ISNUMBER(R38),(IF(AND($P38=$D$5,ISNUMBER($F$9)),$F$9,R38)*$F$8+$F$8*$F$10+$F$11)*(1+$L$8/100),0)) -> 0 | U38: =IF($P38=$D$5,IF(ISNUMBER(R38),(IF(AND($P38=$D$5,ISNUMBER($F$9)),$F$9,R38)*$F$8+$F$8*$F$10+$F$11)*(1+$L$8/100),0),0) -> 0
B39: ¿Un salón o varios? | E39: =IFERROR(IF(INDEX('Fincas 20 km'!$Q$2:$Q$39,$K$5)="","No consta",INDEX('Fincas 20 km'!$Q$2:$Q$39,$K$5)),"—") -> Varios | P39: ='Fincas 20 km'!B28 -> Restaurante San Francisco (El Pardo) | Q39: =ROUND('Fincas 20 km'!F28*$L$9/$L$10*60,0) -> 27 | R39: =IF('Fincas 20 km'!I28="",NA(),'Fincas 20 km'!I28) -> #N/A | T39: =IF($P39=$D$5,0,IF(ISNUMBER(R39),(IF(AND($P39=$D$5,ISNUMBER($F$9)),$F$9,R39)*$F$8+$F$8*$F$10+$F$11)*(1+$L$8/100),0)) -> 0 | U39: =IF($P39=$D$5,IF(ISNUMBER(R39),(IF(AND($P39=$D$5,ISNUMBER($F$9)),$F$9,R39)*$F$8+$F$8*$F$10+$F$11)*(1+$L$8/100),0),0) -> 0
B40: Terraza / jardín | E40: =IFERROR(IF(INDEX('Fincas 20 km'!$R$2:$R$39,$K$5)="","No consta",INDEX('Fincas 20 km'!$R$2:$R$39,$K$5)),"—") -> Sí (jardín y terraza recién reformada) | P40: ='Fincas 20 km'!B29 -> Palacio del Negralejo (Grupo Negralejo) | Q40: =ROUND('Fincas 20 km'!F29*$L$9/$L$10*60,0) -> 27 | R40: =IF('Fincas 20 km'!I29="",NA(),'Fincas 20 km'!I29) -> 150 | T40: =IF($P40=$D$5,0,IF(ISNUMBER(R40),(IF(AND($P40=$D$5,ISNUMBER($F$9)),$F$9,R40)*$F$8+$F$8*$F$10+$F$11)*(1+$L$8/100),0)) -> 19800 | U40: =IF($P40=$D$5,IF(ISNUMBER(R40),(IF(AND($P40=$D$5,ISNUMBER($F$9)),$F$9,R40)*$F$8+$F$8*$F$10+$F$11)*(1+$L$8/100),0),0) -> 0
B41: Cuarto o zona de novios | E41: =IFERROR(IF(INDEX('Fincas 20 km'!$S$2:$S$39,$K$5)="","No consta",INDEX('Fincas 20 km'!$S$2:$S$39,$K$5)),"—") -> Sí – habitaciones del hotel | P41: ='Fincas 20 km'!B30 -> Jardines del Negralejo (Grupo Negralejo) | Q41: =ROUND('Fincas 20 km'!F30*$L$9/$L$10*60,0) -> 27 | R41: =IF('Fincas 20 km'!I30="",NA(),'Fincas 20 km'!I30) -> 150 | T41: =IF($P41=$D$5,0,IF(ISNUMBER(R41),(IF(AND($P41=$D$5,ISNUMBER($F$9)),$F$9,R41)*$F$8+$F$8*$F$10+$F$11)*(1+$L$8/100),0)) -> 19800 | U41: =IF($P41=$D$5,IF(ISNUMBER(R41),(IF(AND($P41=$D$5,ISNUMBER($F$9)),$F$9,R41)*$F$8+$F$8*$F$10+$F$11)*(1+$L$8/100),0),0) -> 0
B42: Ceremonia en la finca | E42: =IFERROR(IF(INDEX('Fincas 20 km'!$T$2:$T$39,$K$5)="","No consta",INDEX('Fincas 20 km'!$T$2:$T$39,$K$5)),"—") -> Sí | P42: ='Fincas 20 km'!B31 -> Finca La Alquería | Q42: =ROUND('Fincas 20 km'!F31*$L$9/$L$10*60,0) -> 29 | R42: =IF('Fincas 20 km'!I31="",NA(),'Fincas 20 km'!I31) -> 100 | T42: =IF($P42=$D$5,0,IF(ISNUMBER(R42),(IF(AND($P42=$D$5,ISNUMBER($F$9)),$F$9,R42)*$F$8+$F$8*$F$10+$F$11)*(1+$L$8/100),0)) -> 13200 | U42: =IF($P42=$D$5,IF(ISNUMBER(R42),(IF(AND($P42=$D$5,ISNUMBER($F$9)),$F$9,R42)*$F$8+$F$8*$F$10+$F$11)*(1+$L$8/100),0),0) -> 0
B43: Alojamiento | E43: =IFERROR(IF(INDEX('Fincas 20 km'!$U$2:$U$39,$K$5)="","No consta",INDEX('Fincas 20 km'!$U$2:$U$39,$K$5)),"—") -> Sí (hotel NH) | P43: ='Fincas 20 km'!B32 -> Finca Las Jarillas | Q43: =ROUND('Fincas 20 km'!F32*$L$9/$L$10*60,0) -> 32 | R43: =IF('Fincas 20 km'!I32="",NA(),'Fincas 20 km'!I32) -> #N/A | T43: =IF($P43=$D$5,0,IF(ISNUMBER(R43),(IF(AND($P43=$D$5,ISNUMBER($F$9)),$F$9,R43)*$F$8+$F$8*$F$10+$F$11)*(1+$L$8/100),0)) -> 0 | U43: =IF($P43=$D$5,IF(ISNUMBER(R43),(IF(AND($P43=$D$5,ISNUMBER($F$9)),$F$9,R43)*$F$8+$F$8*$F$10+$F$11)*(1+$L$8/100),0),0) -> 0
B44: Parking | E44: =IFERROR(IF(INDEX('Fincas 20 km'!$V$2:$V$39,$K$5)="","No consta",INDEX('Fincas 20 km'!$V$2:$V$39,$K$5)),"—") -> No consta | P44: ='Fincas 20 km'!B33 -> El Antiguo Convento de Boadilla del Monte | Q44: =ROUND('Fincas 20 km'!F33*$L$9/$L$10*60,0) -> 33 | R44: =IF('Fincas 20 km'!I33="",NA(),'Fincas 20 km'!I33) -> 145 | T44: =IF($P44=$D$5,0,IF(ISNUMBER(R44),(IF(AND($P44=$D$5,ISNUMBER($F$9)),$F$9,R44)*$F$8+$F$8*$F$10+$F$11)*(1+$L$8/100),0)) -> 19140 | U44: =IF($P44=$D$5,IF(ISNUMBER(R44),(IF(AND($P44=$D$5,ISNUMBER($F$9)),$F$9,R44)*$F$8+$F$8*$F$10+$F$11)*(1+$L$8/100),0),0) -> 0
B45: Horario / eventos al día | E45: =IFERROR(IF(INDEX('Fincas 20 km'!$W$2:$W$39,$K$5)="","No consta",INDEX('Fincas 20 km'!$W$2:$W$39,$K$5)),"—") -> No consta | P45: ='Fincas 20 km'!B34 -> Palacio de Aldovea | Q45: =ROUND('Fincas 20 km'!F34*$L$9/$L$10*60,0) -> 33 | R45: =IF('Fincas 20 km'!I34="",NA(),'Fincas 20 km'!I34) -> #N/A | T45: =IF($P45=$D$5,0,IF(ISNUMBER(R45),(IF(AND($P45=$D$5,ISNUMBER($F$9)),$F$9,R45)*$F$8+$F$8*$F$10+$F$11)*(1+$L$8/100),0)) -> 0 | U45: =IF($P45=$D$5,IF(ISNUMBER(R45),(IF(AND($P45=$D$5,ISNUMBER($F$9)),$F$9,R45)*$F$8+$F$8*$F$10+$F$11)*(1+$L$8/100),0),0) -> 0
B46: Precio publicado | E46: =IFERROR(IF(INDEX('Fincas 20 km'!$H$2:$H$39,$K$5)="","No consta",INDEX('Fincas 20 km'!$H$2:$H$39,$K$5)),"—") -> Menú desde 76 € (promoción bodas.net); facturación mínima 9.000 € | P46: ='Fincas 20 km'!B35 -> Finca Villa María | Q46: =ROUND('Fincas 20 km'!F35*$L$9/$L$10*60,0) -> 34 | R46: =IF('Fincas 20 km'!I35="",NA(),'Fincas 20 km'!I35) -> 145 | T46: =IF($P46=$D$5,0,IF(ISNUMBER(R46),(IF(AND($P46=$D$5,ISNUMBER($F$9)),$F$9,R46)*$F$8+$F$8*$F$10+$F$11)*(1+$L$8/100),0)) -> 19140 | U46: =IF($P46=$D$5,IF(ISNUMBER(R46),(IF(AND($P46=$D$5,ISNUMBER($F$9)),$F$9,R46)*$F$8+$F$8*$F$10+$F$11)*(1+$L$8/100),0),0) -> 0
B47: Observaciones | E47: =IFERROR(IF(INDEX('Fincas 20 km'!$X$2:$X$39,$K$5)="","No consta",INDEX('Fincas 20 km'!$X$2:$X$39,$K$5)),"—") -> El más céntrico de la lista (evita autobús). Opiniones destacan al wedding planner (Roberto) y que es LGTBI+ y vegan friendly. | P47: ='Fincas 20 km'!B36 -> Gasterea Finca Restaurante | Q47: =ROUND('Fincas 20 km'!F36*$L$9/$L$10*60,0) -> 34 | R47: =IF('Fincas 20 km'!I36="",NA(),'Fincas 20 km'!I36) -> 120 | T47: =IF($P47=$D$5,0,IF(ISNUMBER(R47),(IF(AND($P47=$D$5,ISNUMBER($F$9)),$F$9,R47)*$F$8+$F$8*$F$10+$F$11)*(1+$L$8/100),0)) -> 15840 | U47: =IF($P47=$D$5,IF(ISNUMBER(R47),(IF(AND($P47=$D$5,ISNUMBER($F$9)),$F$9,R47)*$F$8+$F$8*$F$10+$F$11)*(1+$L$8/100),0),0) -> 0
B48: Teléfono | E48: =IFERROR(IF(INDEX('Fincas 20 km'!$AB$2:$AB$39,$K$5)="","No consta",INDEX('Fincas 20 km'!$AB$2:$AB$39,$K$5)),"—") -> +34 913 61 02 88 | P48: ='Fincas 20 km'!B37 -> Finca La Constancia | Q48: =ROUND('Fincas 20 km'!F37*$L$9/$L$10*60,0) -> 34 | R48: =IF('Fincas 20 km'!I37="",NA(),'Fincas 20 km'!I37) -> 50 | T48: =IF($P48=$D$5,0,IF(ISNUMBER(R48),(IF(AND($P48=$D$5,ISNUMBER($F$9)),$F$9,R48)*$F$8+$F$8*$F$10+$F$11)*(1+$L$8/100),0)) -> 6600 | U48: =IF($P48=$D$5,IF(ISNUMBER(R48),(IF(AND($P48=$D$5,ISNUMBER($F$9)),$F$9,R48)*$F$8+$F$8*$F$10+$F$11)*(1+$L$8/100),0),0) -> 0
B49: Valoración | E49: ="Google: "&IF(INDEX('Fincas 20 km'!$Y$2:$Y$39,$K$5)="","—",TEXT(INDEX('Fincas 20 km'!$Y$2:$Y$39,$K$5),"0.0")&" ("&INDEX('Fincas 20 km'!$Z$2:$Z$39,$K$5)&" reseñas)")&" · bodas.net: "&IF(INDEX('Fincas 20 km'!$AA$2:$AA$39,$K$5)="","—",INDEX('Fincas 20 km'!$AA$2:$AA$39,$K$5)) -> Google: 4.7 (15 reseñas) · bodas.net: 4,9 (161) | P49: ='Fincas 20 km'!B38 -> Villa Laureana | Q49: =ROUND('Fincas 20 km'!F38*$L$9/$L$10*60,0) -> 37 | R49: =IF('Fincas 20 km'!I38="",NA(),'Fincas 20 km'!I38) -> 120 | T49: =IF($P49=$D$5,0,IF(ISNUMBER(R49),(IF(AND($P49=$D$5,ISNUMBER($F$9)),$F$9,R49)*$F$8+$F$8*$F$10+$F$11)*(1+$L$8/100),0)) -> 15840 | U49: =IF($P49=$D$5,IF(ISNUMBER(R49),(IF(AND($P49=$D$5,ISNUMBER($F$9)),$F$9,R49)*$F$8+$F$8*$F$10+$F$11)*(1+$L$8/100),0),0) -> 0
B50: Enlaces | E50: =HYPERLINK("https://www.google.com/maps/dir/?api=1&origin=Calle+de+Ayala+71,+Madrid&destination="&INDEX('Fincas 20 km'!$AE$2:$AE$39,$K$5)&","&INDEX('Fincas 20 km'!$AF$2:$AF$39,$K$5)&"&travelmode=driving","Ruta y tiempo real") -> Ruta y tiempo real | H50: =INDEX('Fincas 20 km'!$AJ$2:$AJ$39,$K$5) -> Buscar en Instagram | K50: =IFERROR(HYPERLINK(INDEX('Fincas 20 km'!$AC$2:$AC$39,$K$5),"Ficha de origen"),"") -> Ficha de origen | P50: ='Fincas 20 km'!B39 -> Señorío de Ajuria | Q50: =ROUND('Fincas 20 km'!F39*$L$9/$L$10*60,0) -> 37 | R50: =IF('Fincas 20 km'!I39="",NA(),'Fincas 20 km'!I39) -> 90 | T50: =IF($P50=$D$5,0,IF(ISNUMBER(R50),(IF(AND($P50=$D$5,ISNUMBER($F$9)),$F$9,R50)*$F$8+$F$8*$F$10+$F$11)*(1+$L$8/100),0)) -> 11880 | U50: =IF($P50=$D$5,IF(ISNUMBER(R50),(IF(AND($P50=$D$5,ISNUMBER($F$9)),$F$9,R50)*$F$8+$F$8*$F$10+$F$11)*(1+$L$8/100),0),0) -> 0
B52: Dónde queda frente a las demás

Sheet Fincas 20 km
A1: Nº | B1: Nombre | C1: Tipo de espacio | D1: Zona / municipio | E1: Dirección | F1: Distancia en línea recta (km) | G1: ¿Dentro del radio? | H1: Precio orientativo | I1: Precio menú desde (€/invitado) | J1: ="Coste menú orientativo para "&Notas!$B$7&" invitados (€)" -> Coste menú orientativo para 120 invitados (€) | K1: Aforo mín. | L1: Aforo máx. | M1: Aforo (detalle) | N1: Catering (quién lo da) | O1: ¿Catering libre? | P1: Salones / espacios | Q1: ¿Un salón o varios? | R1: Terraza / jardín | S1: Cuarto o zona de novios | T1: Ceremonia en la finca | U1: Alojamiento | V1: Parking | W1: Horario / nº eventos | X1: Observaciones | Y1: Google (nota) | Z1: Google (nº reseñas) | AA1: bodas.net (nota y opiniones) | AB1: Teléfono | AC1: Fuente principal | AD1: Ver en Google Maps | AE1: Latitud | AF1: Longitud | AG1: Tiempo estimado en coche (min) | AH1: Ruta en Google Maps (tiempo real) | AI1: Instagram (@usuario) | AJ1: Instagram: abrir / buscar
A2: 1 | B2: El Jardín de Ventas | C2: Jardín del hotel NH Madrid Ventas | D2: Madrid – Ventas (Salamanca) | E2: C/ de Biarritz 2, 28028 Madrid | F2: =ROUND(6371*2*ASIN(SQRT(SIN(RADIANS(AE2-Notas!$B$4)/2)^2+COS(RADIANS(Notas!$B$4))*COS(RADIANS(AE2))*SIN(RADIANS(AF2-Notas!$B$5)/2)^2)),1) -> 1.3 | G2: =IF(F2<=Notas!$B$6,"Sí","No") -> Sí | H2: Menú desde 76 € (promoción bodas.net); facturación mínima 9.000 € | I2: 76 | J2: =IF(ISNUMBER(I2),I2*Notas!$B$7,"") -> 9120 | M2: No publicado | N2: Cocina del hotel NH Ventas | O2: No (catering del hotel); tarta propia permitida | P2: Jardín (ceremonia civil y cóctel) + terraza reformada + salón del hotel; banquete también al aire libre | Q2: Varios | R2: Sí (jardín y terraza recién reformada) | S2: Sí – habitaciones del hotel | T2: Sí | U2: Sí (hotel NH) | V2: No consta | W2: No consta | X2: El más céntrico de la lista (evita autobús). Opiniones destacan al wedding planner (Roberto) y que es LGTBI+ y vegan friendly. | Y2: 4.7 | Z2: 15 | AA2: 4,9 (161) | AB2: +34 913 61 02 88 | AC2: https://www.bodas.net/hoteles/jardin-de-ventas--e7903 | AD2: =HYPERLINK("https://www.google.com/maps/search/?api=1&query="&AE2&","&AF2,"Abrir mapa") -> Abrir mapa | AE2: 40.435353 | AF2: -3.6638616 | AG2: =ROUND(F2*Notas!$B$8/Notas!$B$9*60,0) -> 3 | AH2: =HYPERLINK("https://www.google.com/maps/dir/?api=1&origin=Calle+de+Ayala+71,+Madrid&destination="&AE2&","&AF2&"&travelmode=driving","Ver ruta y tiempo") -> Ver ruta y tiempo | AJ2: =IF(AI2="",HYPERLINK("https://www.google.com/search?q=site%3Ainstagram.com+El+Jard%C3%ADn+de+Ventas+bodas","Buscar en Instagram"),HYPERLINK("https://instagram.com/"&SUBSTITUTE(AI2,"@",""),AI2)) -> Buscar en Instagram
A3: 2 | B3: Real Fábrica de Tapices & El Puchero de Plata | C3: Espacio histórico con jardines (Patrimonio Nacional) | D3: Madrid – Retiro | E3: C/ Fuenterrabía 2, 28014 Madrid | F3: =ROUND(6371*2*ASIN(SQRT(SIN(RADIANS(AE3-Notas!$B$4)/2)^2+COS(RADIANS(Notas!$B$4))*COS(RADIANS(AE3))*SIN(RADIANS(AF3-Notas!$B$5)/2)^2)),1) -> 2.4 | G3: =IF(F3<=Notas!$B$6,"Sí","No") -> Sí | H3: Menú desde 138 €/invitado | I3: 138 | J3: =IF(ISNUMBER(I3),I3*Notas!$B$7,"") -> 16560 | L3: 450 | M3: Hasta 450 | N3: El Puchero de Plata (catering asociado al espacio) | O3: No (catering asociado) – confirmar | P3: Varias salas y zonas + jardines cuidados | Q3: Varios | R3: Sí (jardines) | S3: No consta – preguntar | T3: Sí (se puede montar la ceremonia en el lugar) | U3: No | V3: No consta | W3: No consta | X3: Fábrica de tapices s. XVIII en activo. Céntrico. | AA3: 4,9 (174) | AB3: +34 914 34 05 50 | AC3: https://www.bodas.net/fincas/real-fabrica-de-tapices-&-el-puchero-de-plata--e76351 | AD3: =HYPERLINK("https://www.google.com/maps/search/?api=1&query="&AE3&","&AF3,"Abrir mapa") -> Abrir mapa | AE3: 40.40615 | AF3: -3.6825436 | AG3: =ROUND(F3*Notas!$B$8/Notas!$B$9*60,0) -> 5 | AH3: =HYPERLINK("https://www.google.com/maps/dir/?api=1&origin=Calle+de+Ayala+71,+Madrid&destination="&AE3&","&AF3&"&travelmode=driving","Ver ruta y tiempo") -> Ver ruta y tiempo | AJ3: =IF(AI3="",HYPERLINK("https://www.google.com/search?q=site%3Ainstagram.com+Real+F%C3%A1brica+de+Tapices+++El+Puchero+de+Plata+bodas","Buscar en Instagram"),HYPERLINK("https://instagram.com/"&SUBSTITUTE(AI3,"@",""),AI3)) -> Buscar en Instagram
A4: 3 | B4: La Quinta by Madrid Catering | C4: Quinta / finca urbana | D4: Madrid – Hortaleza | E4: C/ de Belisana 17, 28043 Madrid | F4: =ROUND(6371*2*ASIN(SQRT(SIN(RADIANS(AE4-Notas!$B$4)/2)^2+COS(RADIANS(Notas!$B$4))*COS(RADIANS(AE4))*SIN(RADIANS(AF4-Notas!$B$5)/2)^2)),1) -> 3.9 | G4: =IF(F4<=Notas!$B$6,"Sí","No") -> Sí | H4: Menús 14–100 €/invitado según bodas.net (el tramo bajo será infantil/cóctel; pedir presupuesto) | J4: =IF(ISNUMBER(I4),I4*Notas!$B$7,"") | K4: 10 | L4: 165 | M4: 10–165 | N4: Madrid Catering (diseñan menú, decoración y coordinación) | O4: No (catering de la casa) | P4: Finca con jardín y espacios interiores; montaje y decoración personalizables | Q4: Consultar | R4: Sí (jardín) | S4: No consta – preguntar | T4: Consultar | U4: No | V4: No consta | W4: No consta | X4: Eventos a medida con coordinación integral el día de la boda. Opiniones destacan la flexibilidad. | Y4: 4.5 | Z4: 61 | AA4: — | AB4: +34 722 75 66 03 | AC4: https://www.bodas.net/salones-de-boda/la-quinta-by-madrid-catering--e252629 | AD4: =HYPERLINK("https://www.google.com/maps/search/?api=1&query="&AE4&","&AF4,"Abrir mapa") -> Abrir mapa | AE4: 40.458634 | AF4: -3.6553225 | AG4: =ROUND(F4*Notas!$B$8/Notas!$B$9*60,0) -> 8 | AH4: =HYPERLINK("https://www.google.com/maps/dir/?api=1&origin=Calle+de+Ayala+71,+Madrid&destination="&AE4&","&AF4&"&travelmode=driving","Ver ruta y tiempo") -> Ver ruta y tiempo | AJ4: =IF(AI4="",HYPERLINK("https://www.google.com/search?q=site%3Ainstagram.com+La+Quinta+by+Madrid+Catering+bodas","Buscar en Instagram"),HYPERLINK("https://instagram.com/"&SUBSTITUTE(AI4,"@",""),AI4)) -> Buscar en Instagram
A5: 4 | B5: Quinta de los Molinos by Elba | C5: Hotel con jardines (junto al parque Quinta de los Molinos) | D5: Madrid – San Blas | E5: C/ de Alcalá 476, 28027 Madrid | F5: =ROUND(6371*2*ASIN(SQRT(SIN(RADIANS(AE5-Notas!$B$4)/2)^2+COS(RADIANS(Notas!$B$4))*COS(RADIANS(AE5))*SIN(RADIANS(AF5-Notas!$B$5)/2)^2)),1) -> 4 | G5: =IF(F5<=Notas!$B$6,"Sí","No") -> Sí | H5: Menú desde 138 €/invitado | I5: 138 | J5: =IF(ISNUMBER(I5),I5*Notas!$B$7,"") -> 16560 | K5: 60 | M5: Desde 60 invitados (máx. no publicado) | N5: Cocina del hotel | O5: No (catering del hotel) | P5: Varias instalaciones: ceremonia, cóctel y banquete en espacios distintos; jardín y terraza | Q5: Varios | R5: Sí (jardín y terraza) | S5: Sí – habitaciones del hotel | T5: Sí (jardín) | U5: Sí (hotel) | V5: Sí (gestionan plazas) | W5: No consta | X5: Boda campestre sin salir de la ciudad; flexibles con menús, cócteles y horas de barra libre. | Y5: 4.4 | Z5: 28 | AA5: 4,8 (44) | AB5: +34 913 75 68 07 | AC5: https://www.bodas.net/fincas/quinta-de-los-molinos-by-elba--e109054 | AD5: =HYPERLINK("https://www.google.com/maps/search/?api=1&query="&AE5&","&AF5,"Abrir mapa") -> Abrir mapa | AE5: 40.439352 | AF5: -3.6315274 | AG5: =ROUND(F5*Notas!$B$8/Notas!$B$9*60,0) -> 8 | AH5: =HYPERLINK("https://www.google.com/maps/dir/?api=1&origin=Calle+de+Ayala+71,+Madrid&destination="&AE5&","&AF5&"&travelmode=driving","Ver ruta y tiempo") -> Ver ruta y tiempo | AJ5: =IF(AI5="",HYPERLINK("https://www.google.com/search?q=site%3Ainstagram.com+Quinta+de+los+Molinos+by+Elba+bodas","Buscar en Instagram"),HYPERLINK("https://instagram.com/"&SUBSTITUTE(AI5,"@",""),AI5)) -> Buscar en Instagram
A6: 5 | B6: Palacete / Complejo Duques de Pastrana | C6: Palacete s. XIX con jardines | D6: Madrid – Chamartín | E6: P.º de la Habana 208 / C/ Platerías 2, 28016 Madrid | F6: =ROUND(6371*2*ASIN(SQRT(SIN(RADIANS(AE6-Notas!$B$4)/2)^2+COS(RADIANS(Notas!$B$4))*COS(RADIANS(AE6))*SIN(RADIANS(AF6-Notas!$B$5)/2)^2)),1) -> 4.4 | G6: =IF(F6<=Notas!$B$6,"Sí","No") -> Sí | H6: No publicado (pedir presupuesto) | J6: =IF(ISNUMBER(I6),I6*Notas!$B$7,"") | L6: 740 | M6: Jardines del palacete: 220 banquete / 500 cóctel; otros jardines 500; Sala Polivalente 740 | N6: Vilaplana Catering (Compass Group), que gestiona los eventos del complejo | O6: No (catering del complejo) | P6: Palacete (Sala Roja 150, Balcones 125, Verde 110) + Sala Polivalente + salas de exposiciones + auditorio; 17 salas | Q6: Varios | R6: Sí (porche de columnas y 1.200 m² de jardines) | S6: Hay salas pequeñas en el palacete – preguntar | T6: Sí (jardines) | U6: No | V6: Sí | W6: No consta | X6: Monumento de Interés Cultural; metro Duque de Pastrana (L9) al lado. Ofrecen también wedding planner y decoración. Contacto: comercial@complejoduquesdepastrana.es | Y6: 4.4 | Z6: 912 | AA6: — | AB6: +34 913 53 61 51 | AC6: https://www.timeout.es/madrid/es/que-hacer/palacio-duques-de-pastrana | AD6: =HYPERLINK("https://www.google.com/maps/search/?api=1&query="&AE6&","&AF6,"Abrir mapa") -> Abrir mapa | AE6: 40.467403 | AF6: -3.6787017 | AG6: =ROUND(F6*Notas!$B$8/Notas!$B$9*60,0) -> 9 | AH6: =HYPERLINK("https://www.google.com/maps/dir/?api=1&origin=Calle+de+Ayala+71,+Madrid&destination="&AE6&","&AF6&"&travelmode=driving","Ver ruta y tiempo") -> Ver ruta y tiempo | AJ6: =IF(AI6="",HYPERLINK("https://www.google.com/search?q=site%3Ainstagram.com+Palacete+%2F+Complejo+Duques+de+Pastrana+bodas","Buscar en Instagram"),HYPERLINK("https://instagram.com/"&SUBSTITUTE(AI6,"@",""),AI6)) -> Buscar en Instagram
A7: 6 | B7: Café de Oriente Museo del Traje | C7: Museo con terrazas y jardín | D7: Madrid – Moncloa (Ciudad Universitaria) | E7: Av. de Juan de Herrera 2, 28040 Madrid | F7: =ROUND(6371*2*ASIN(SQRT(SIN(RADIANS(AE7-Notas!$B$4)/2)^2+COS(RADIANS(Notas!$B$4))*COS(RADIANS(AE7))*SIN(RADIANS(AF7-Notas!$B$5)/2)^2)),1) -> 4.7 | G7: =IF(F7<=Notas!$B$6,"Sí","No") -> Sí | H7: Menú desde 140 €/invitado (promoción todo incluido desde 170 €) | I7: 140 | J7: =IF(ISNUMBER(I7),I7*Notas!$B$7,"") -> 16800 | K7: 50 | L7: 700 | M7: 50–700 | N7: Café de Oriente / Alabardero Catering | O7: No (catering de la casa) | P7: Varios: Sala Oriente, Terraza Oriente, Terraza Balenciaga, espacio Cardenal Cisneros | Q7: Varios | R7: Sí (varias terrazas) | S7: No consta – preguntar | T7: Consultar | U7: No | V7: No consta | W7: No consta | X7: Buena opción para bodas tipo cóctel con puestos temáticos. | Y7: 4.2 | Z7: 2049 | AA7: 4,8 (57) | AB7: +34 915 50 20 55 | AC7: https://www.bodas.net/fincas/cafe-de-oriente-museo-del-traje--e47950 | AD7: =HYPERLINK("https://www.google.com/maps/search/?api=1&query="&AE7&","&AF7,"Abrir mapa") -> Abrir mapa | AE7: 40.439845 | AF7: -3.7294501 | AG7: =ROUND(F7*Notas!$B$8/Notas!$B$9*60,0) -> 9 | AH7: =HYPERLINK("https://www.google.com/maps/dir/?api=1&origin=Calle+de+Ayala+71,+Madrid&destination="&AE7&","&AF7&"&travelmode=driving","Ver ruta y tiempo") -> Ver ruta y tiempo | AJ7: =IF(AI7="",HYPERLINK("https://www.google.com/search?q=site%3Ainstagram.com+Caf%C3%A9+de+Oriente+Museo+del+Traje+bodas","Buscar en Instagram"),HYPERLINK("https://instagram.com/"&SUBSTITUTE(AI7,"@",""),AI7)) -> Buscar en Instagram
A8: 7 | B8: Casa de Burgos | C8: Castillo-pabellón con jardín (Casa de Campo) | D8: Madrid – Casa de Campo | E8: C/ Principal de Provincias 3, 28011 Madrid | F8: =ROUND(6371*2*ASIN(SQRT(SIN(RADIANS(AE8-Notas!$B$4)/2)^2+COS(RADIANS(Notas!$B$4))*COS(RADIANS(AE8))*SIN(RADIANS(AF8-Notas!$B$5)/2)^2)),1) -> 4.9 | G8: =IF(F8<=Notas!$B$6,"Sí","No") -> Sí | H8: Menú desde 100 €/invitado | I8: 100 | J8: =IF(ISNUMBER(I8),I8*Notas!$B$7,"") -> 12000 | K8: 50 | L8: 350 | M8: 50–350 (ficha de eventos: hasta 400 banquete / 630 cóctel) | N8: Grupo Araceli ("Casa de Burgos de Araceli") | O8: No (catering de la casa) | P8: Salón principal (450 m²) + salones Lavanda (60 m²) y Jazmín (50 m²) + patio porticado + jardín 800 m² | Q8: Varios | R8: Sí – jardín/terraza con vistas al Palacio Real y la Almudena | S8: 2 salones pequeños (Lavanda/Jazmín) – preguntar si se ceden a los novios | T8: Sí (jardín con vistas) | U8: No | V8: No consta | W8: No consta | X8: Réplica de castillo s. XIV construida en 1953-56 para la Feria del Campo. | Y8: 4.5 | Z8: 596 | AA8: 4,9 (201) | AB8: +34 914 64 40 77 | AC8: https://www.bodas.net/fincas/casa-de-burgos--e121847 | AD8: =HYPERLINK("https://www.google.com/maps/search/?api=1&query="&AE8&","&AF8,"Abrir mapa") -> Abrir mapa | AE8: 40.414464 | AF8: -3.7308012 | AG8: =ROUND(F8*Notas!$B$8/Notas!$B$9*60,0) -> 10 | AH8: =HYPERLINK("https://www.google.com/maps/dir/?api=1&origin=Calle+de+Ayala+71,+Madrid&destination="&AE8&","&AF8&"&travelmode=driving","Ver ruta y tiempo") -> Ver ruta y tiempo | AJ8: =IF(AI8="",HYPERLINK("https://www.google.com/search?q=site%3Ainstagram.com+Casa+de+Burgos+bodas","Buscar en Instagram"),HYPERLINK("https://instagram.com/"&SUBSTITUTE(AI8,"@",""),AI8)) -> Buscar en Instagram
A9: 8 | B9: La Masía de José Luis | C9: Finca urbana con jardín | D9: Madrid – Casa de Campo (Puerta del Ángel) | E9: P.º de la Puerta del Ángel 3, 28011 Madrid | F9: =ROUND(6371*2*ASIN(SQRT(SIN(RADIANS(AE9-Notas!$B$4)/2)^2+COS(RADIANS(Notas!$B$4))*COS(RADIANS(AE9))*SIN(RADIANS(AF9-Notas!$B$5)/2)^2)),1) -> 4.9 | G9: =IF(F9<=Notas!$B$6,"Sí","No") -> Sí | H9: Menú desde 140 €/invitado | I9: 140 | J9: =IF(ISNUMBER(I9),I9*Notas!$B$7,"") -> 16800 | K9: 60 | L9: 440 | M9: 60–440 | N9: Grupo José Luis (catering propio) | O9: No (catering de la casa) | P9: Varios: Zaguán, Invernadero, Salón Espejos (mesa imperial), carpa; 2.500 m² de jardín y terrazas | Q9: Varios | R9: Sí (jardín y terrazas) | S9: No consta – preguntar | T9: Consultar | U9: No | V9: No consta | W9: No consta | X9: Finca de 2.828 m² rodeada de vegetación. | Y9: 4.5 | Z9: 1105 | AA9: 4,9 (91) | AB9: +34 914 79 86 15 | AC9: https://www.bodas.net/fincas/la-masia-de-jose-luis--e3442 | AD9: =HYPERLINK("https://www.google.com/maps/search/?api=1&query="&AE9&","&AF9,"Abrir mapa") -> Abrir mapa | AE9: 40.415241 | AF9: -3.7311611 | AG9: =ROUND(F9*Notas!$B$8/Notas!$B$9*60,0) -> 10 | AH9: =HYPERLINK("https://www.google.com/maps/dir/?api=1&origin=Calle+de+Ayala+71,+Madrid&destination="&AE9&","&AF9&"&travelmode=driving","Ver ruta y tiempo") -> Ver ruta y tiempo | AJ9: =IF(AI9="",HYPERLINK("https://www.google.com/search?q=site%3Ainstagram.com+La+Mas%C3%ADa+de+Jos%C3%A9+Luis+bodas","Buscar en Instagram"),HYPERLINK("https://instagram.com/"&SUBSTITUTE(AI9,"@",""),AI9)) -> Buscar en Instagram
A10: 9 | B10: Club de Campo Villa de Madrid | C10: Club deportivo con jardines | D10: Madrid – Moncloa-Aravaca | E10: Ctra. de Castilla s/n, 28040 Madrid | F10: =ROUND(6371*2*ASIN(SQRT(SIN(RADIANS(AE10-Notas!$B$4)/2)^2+COS(RADIANS(Notas!$B$4))*COS(RADIANS(AE10))*SIN(RADIANS(AF10-Notas!$B$5)/2)^2)),1) -> 5.8 | G10: =IF(F10<=Notas!$B$6,"Sí","No") -> Sí | H10: Alquiler de espacio: Chalet del Golf 2.500 € (IVA incl.); otro espacio desde 1.000 € + IVA según invitados; + menú (pedir presupuesto) | J10: =IF(ISNUMBER(I10),I10*Notas!$B$7,"") | M10: No publicado | N10: Catering del club (cocina del chef Iván Sáez); en opiniones también Cavalier Catering | O10: No – no se admiten comida ni bebida del exterior | P10: 2 espacios: La Cristalera (Hípica) y el Chalet del Golf, con jardín y vistas a Madrid iluminado; carpas con proveedor del club | Q10: Varios | R10: Sí (jardín; vistas a Madrid) | S10: No consta – preguntar | T10: Consultar | U10: No | V10: Sí, dentro del club | W10: 4 h de barra libre incluidas (hora extra aparte) | X10: Dossier «Bodas 2026» del club: reserva = alquiler del espacio + contrato de catering con 25% de depósito; incluye decoración floral de mesas y degustación (6 personas en bodas de 100+); menú infantil 50 €; jamón con cortador en bodas de 150+. Descuentos para abonados. | Y10: 4.3 | Z10: 891 | AA10: — | AB10: — | AC10: https://www.ccvm.es/sites/default/files/users/user7/BODAS%202026.pdf | AD10: =HYPERLINK("https://www.google.com/maps/search/?api=1&query="&AE10&","&AF10,"Abrir mapa") -> Abrir mapa | AE10: 40.438728 | AF10: -3.742673 | AG10: =ROUND(F10*Notas!$B$8/Notas!$B$9*60,0) -> 11 | AH10: =HYPERLINK("https://www.google.com/maps/dir/?api=1&origin=Calle+de+Ayala+71,+Madrid&destination="&AE10&","&AF10&"&travelmode=driving","Ver ruta y tiempo") -> Ver ruta y tiempo | AJ10: =IF(AI10="",HYPERLINK("https://www.google.com/search?q=site%3Ainstagram.com+Club+de+Campo+Villa+de+Madrid+bodas","Buscar en Instagram"),HYPERLINK("https://instagram.com/"&SUBSTITUTE(AI10,"@",""),AI10)) -> Buscar en Instagram
A11: 10 | B11: Mirador del Olivar | C11: Club de golf con jardines (Olivar de la Hinojosa) | D11: Madrid – Barajas (Campo de las Naciones) | E11: Vía de Dublín s/n, 28042 Madrid | F11: =ROUND(6371*2*ASIN(SQRT(SIN(RADIANS(AE11-Notas!$B$4)/2)^2+COS(RADIANS(Notas!$B$4))*COS(RADIANS(AE11))*SIN(RADIANS(AF11-Notas!$B$5)/2)^2)),1) -> 7.2 | G11: =IF(F11<=Notas!$B$6,"Sí","No") -> Sí | H11: Menú desde 99 €/invitado | I11: 99 | J11: =IF(ISNUMBER(I11),I11*Notas!$B$7,"") -> 11880 | K11: 50 | L11: 520 | M11: 50–520 | N11: Restaurante del club | O11: No (catering de la casa) | P11: Salón + carpa exterior; ceremonia exterior o interior | Q11: Varios | R11: Sí (carpa, jardín y campo de golf para fotos) | S11: No consta – preguntar | T11: Sí (exterior e interior) | U11: No | V11: Sí | W11: No consta | X11: Vistas al campo de golf. Cerca del aeropuerto. | Y11: 4.1 | Z11: 83 | AA11: 4,9 (96) | AB11: — | AC11: https://www.bodas.net/fincas/mirador-del-olivar--e16700 | AD11: =HYPERLINK("https://www.google.com/maps/search/?api=1&query="&AE11&","&AF11,"Abrir mapa") -> Abrir mapa | AE11: 40.469352 | AF11: -3.6104488 | AG11: =ROUND(F11*Notas!$B$8/Notas!$B$9*60,0) -> 14 | AH11: =HYPERLINK("https://www.google.com/maps/dir/?api=1&origin=Calle+de+Ayala+71,+Madrid&destination="&AE11&","&AF11&"&travelmode=driving","Ver ruta y tiempo") -> Ver ruta y tiempo | AJ11: =IF(AI11="",HYPERLINK("https://www.google.com/search?q=site%3Ainstagram.com+Mirador+del+Olivar+bodas","Buscar en Instagram"),HYPERLINK("https://instagram.com/"&SUBSTITUTE(AI11,"@",""),AI11)) -> Buscar en Instagram
A12: 11 | B12: Club de Tiro de Madrid | C12: Finca en el Monte de El Pardo | D12: Madrid – El Pardo | E12: Ctra. Madrid-El Pardo M-605 km 1,2, 28035 Madrid | F12: =ROUND(6371*2*ASIN(SQRT(SIN(RADIANS(AE12-Notas!$B$4)/2)^2+COS(RADIANS(Notas!$B$4))*COS(RADIANS(AE12))*SIN(RADIANS(AF12-Notas!$B$5)/2)^2)),1) -> 8.9 | G12: =IF(F12<=Notas!$B$6,"Sí","No") -> Sí | H12: Menú 130–155 €/invitado | I12: 130 | J12: =IF(ISNUMBER(I12),I12*Notas!$B$7,"") -> 15600 | K12: 80 | L12: 600 | M12: 80–600 | N12: Life Gourmet / Ramón Freixa Catering (cocina propia) | O12: No – exclusivo (no se alquila solo el espacio) | P12: 2 espacios independientes (Colonial e Invernadero), cada uno con parking, entrada y jardines propios; carpa y zona de baile | Q12: Varios | R12: Sí (terraza, jardines y carpa) | S12: Hay baño/zona de novia (según opiniones) – confirmar sala | T12: Sí, ceremonia civil en jardines | U12: No | V12: Sí | W12: Hasta las 05:00 · 1 evento al día | X12: Exclusividad también de música. Barra libre incluida (con límite de hora). Tarta propia permitida con registro sanitario. 6 Wedding Awards. | Y12: 4.3 | Z12: 1436 | AA12: 4,8 (184) | AB12: +34 913 16 11 69 | AC12: https://www.bodas.net/fincas/club-de-tiro--e81609 | AD12: =HYPERLINK("https://www.google.com/maps/search/?api=1&query="&AE12&","&AF12,"Abrir mapa") -> Abrir mapa | AE12: 40.488892 | AF12: -3.7435091 | AG12: =ROUND(F12*Notas!$B$8/Notas!$B$9*60,0) -> 17 | AH12: =HYPERLINK("https://www.google.com/maps/dir/?api=1&origin=Calle+de+Ayala+71,+Madrid&destination="&AE12&","&AF12&"&travelmode=driving","Ver ruta y tiempo") -> Ver ruta y tiempo | AJ12: =IF(AI12="",HYPERLINK("https://www.google.com/search?q=site%3Ainstagram.com+Club+de+Tiro+de+Madrid+bodas","Buscar en Instagram"),HYPERLINK("https://instagram.com/"&SUBSTITUTE(AI12,"@",""),AI12)) -> Buscar en Instagram
A13: 12 | B13: Fuentearcos | C13: Finca-restaurante con jardines | D13: Madrid – Vicálvaro | E13: Ctra. Vicálvaro a Rivas km 2, 28052 Madrid | F13: =ROUND(6371*2*ASIN(SQRT(SIN(RADIANS(AE13-Notas!$B$4)/2)^2+COS(RADIANS(Notas!$B$4))*COS(RADIANS(AE13))*SIN(RADIANS(AF13-Notas!$B$5)/2)^2)),1) -> 9.5 | G13: =IF(F13<=Notas!$B$6,"Sí","No") -> Sí | H13: Menú desde 120 €/invitado | I13: 120 | J13: =IF(ISNUMBER(I13),I13*Notas!$B$7,"") -> 14400 | K13: 20 | L13: 350 | M13: 20–350 | N13: Cocina propia del restaurante | O13: No (catering de la casa) – confirmar | P13: Varios espacios (p. ej. Espacio/Salón Arcos con cristalera) y jardines | Q13: Varios | R13: Sí (jardines) | S13: No consta – preguntar | T13: Sí (Jardín Arcos) | U13: No | V13: Sí | W13: No consta | X13: Apta para bodas muy pequeñas (desde 20). 5 promociones activas en bodas.net. | Y13: 4.4 | Z13: 2647 | AA13: 4,9 (405) | AB13: +34 917 76 55 17 | AC13: https://www.bodas.net/fincas/fuentearcos--e1946 | AD13: =HYPERLINK("https://www.google.com/maps/search/?api=1&query="&AE13&","&AF13,"Abrir mapa") -> Abrir mapa | AE13: 40.392734 | AF13: -3.5741806 | AG13: =ROUND(F13*Notas!$B$8/Notas!$B$9*60,0) -> 19 | AH13: =HYPERLINK("https://www.google.com/maps/dir/?api=1&origin=Calle+de+Ayala+71,+Madrid&destination="&AE13&","&AF13&"&travelmode=driving","Ver ruta y tiempo") -> Ver ruta y tiempo | AJ13: =IF(AI13="",HYPERLINK("https://www.google.com/search?q=site%3Ainstagram.com+Fuentearcos+bodas","Buscar en Instagram"),HYPERLINK("https://instagram.com/"&SUBSTITUTE(AI13,"@",""),AI13)) -> Buscar en Instagram
A14: 13 | B14: Finca Solimpar | C14: Finca con hotel | D14: Leganés | E14: Ctra. de Toledo A-42 km 8, 28916 Leganés | F14: =ROUND(6371*2*ASIN(SQRT(SIN(RADIANS(AE14-Notas!$B$4)/2)^2+COS(RADIANS(Notas!$B$4))*COS(RADIANS(AE14))*SIN(RADIANS(AF14-Notas!$B$5)/2)^2)),1) -> 9.7 | G14: =IF(F14<=Notas!$B$6,"Sí","No") -> Sí | H14: Menú desde 90 €/invitado (bodas.net) | I14: 90 | J14: =IF(ISNUMBER(I14),I14*Notas!$B$7,"") -> 10800 | K14: 50 | L14: 300 | M14: 50–300 o más (bodas.net); banquete hasta ~400 según ficha de eventos | N14: Cocina propia del restaurante | O14: No (catering de la casa) | P14: Varios salones interiores modulares con acceso directo a jardines | Q14: Varios | R14: Sí (jardines con césped) | S14: Sí – habitaciones del hotel | T14: Sí (jardín) | U14: Sí (hotel, 32 habitaciones) | V14: Sí | W14: No consta | X14: A 10 min del centro por la A-42. | Y14: 4.4 | Z14: 2451 | AA14: 4,7 (350) | AB14: +34 913 41 91 25 | AC14: https://www.bodas.net/fincas/finca-solimpar--e2670 | AD14: =HYPERLINK("https://www.google.com/maps/search/?api=1&query="&AE14&","&AF14,"Abrir mapa") -> Abrir mapa | AE14: 40.348365 | AF14: -3.7242015 | AG14: =ROUND(F14*Notas!$B$8/Notas!$B$9*60,0) -> 19 | AH14: =HYPERLINK("https://www.google.com/maps/dir/?api=1&origin=Calle+de+Ayala+71,+Madrid&destination="&AE14&","&AF14&"&travelmode=driving","Ver ruta y tiempo") -> Ver ruta y tiempo | AJ14: =IF(AI14="",HYPERLINK("https://www.google.com/search?q=site%3Ainstagram.com+Finca+Solimpar+bodas","Buscar en Instagram"),HYPERLINK("https://instagram.com/"&SUBSTITUTE(AI14,"@",""),AI14)) -> Buscar en Instagram
A15: 14 | B15: El Jardín de Somontes (Eventos Somontes) | C15: Jardín para eventos con piscina y carpa | D15: Madrid – El Pardo (Somontes) | E15: Ctra. Madrid-El Pardo km 3,4, 28035 Madrid | F15: =ROUND(6371*2*ASIN(SQRT(SIN(RADIANS(AE15-Notas!$B$4)/2)^2+COS(RADIANS(Notas!$B$4))*COS(RADIANS(AE15))*SIN(RADIANS(AF15-Notas!$B$5)/2)^2)),1) -> 9.7 | G15: =IF(F15<=Notas!$B$6,"Sí","No") -> Sí | H15: No publicado (depende del catering elegido) | J15: =IF(ISNUMBER(I15),I15*Notas!$B$7,"") | K15: 150 | L15: 400 | M15: 150–400 (recargo de 20 €/comensal por debajo de 150) | N15: Trabaja con caterings colaboradores (Catering Mallorca, Artigot Catering) | O15: Lista de caterings (no libre del todo) – pago fijo de 900 € si se elige Mallorca | P15: Jardín (ceremonia y cóctel) + espacio interior (banquete) + gran carpa junto a la piscina (barra libre) | Q15: Varios | R15: Sí (jardín, carpa y piscina) | S15: No consta – preguntar | T15: Sí, ceremonia civil en el jardín | U15: No | V15: No consta | W15: No consta | X15: Mínimo alto (150 invitados). Una de las pocas opciones dentro del radio que no ata a un único catering. | Y15: 4.5 | Z15: 19 | AA15: — | AB15: +34 600 51 65 61 | AC15: https://www.bodas.net/restaurantes/el-jardin-de-somontes--e193863 | AD15: =HYPERLINK("https://www.google.com/maps/search/?api=1&query="&AE15&","&AF15,"Abrir mapa") -> Abrir mapa | AE15: 40.48961 | AF15: -3.756931 | AG15: =ROUND(F15*Notas!$B$8/Notas!$B$9*60,0) -> 19 | AH15: =HYPERLINK("https://www.google.com/maps/dir/?api=1&origin=Calle+de+Ayala+71,+Madrid&destination="&AE15&","&AF15&"&travelmode=driving","Ver ruta y tiempo") -> Ver ruta y tiempo | AJ15: =IF(AI15="",HYPERLINK("https://www.google.com/search?q=site%3Ainstagram.com+El+Jard%C3%ADn+de+Somontes++Eventos+Somontes+bodas","Buscar en Instagram"),HYPERLINK("https://instagram.com/"&SUBSTITUTE(AI15,"@",""),AI15)) -> Buscar en Instagram
A16: 15 | B16: La Casa de Mónico | C16: Finca solariega (1946) con jardín inglés | D16: Madrid – Aravaca | E16: C/ Cabeza de Manzaneda 105 (A-6 km 9,5), 28023 Madrid | F16: =ROUND(6371*2*ASIN(SQRT(SIN(RADIANS(AE16-Notas!$B$4)/2)^2+COS(RADIANS(Notas!$B$4))*COS(RADIANS(AE16))*SIN(RADIANS(AF16-Notas!$B$5)/2)^2)),1) -> 9.8 | G16: =IF(F16<=Notas!$B$6,"Sí","No") -> Sí | H16: Menú desde 185 €/invitado | I16: 185 | J16: =IF(ISNUMBER(I16),I16*Notas!$B$7,"") -> 22200 | K16: 50 | L16: 600 | M16: 50–600 (ficha de eventos: 670 interior / 2.500 exterior) | N16: Mónico Catering (Grupo Mónico) | O16: No – exclusivo (condiciones especiales si no se llega al mínimo) | P16: 5 salas/espacios + jardín inglés de 30.000 m² | Q16: Varios | R16: Sí (jardines) | S16: No consta – preguntar | T16: Sí (jardín) | U16: No | V16: Sí (380 plazas) | W16: No consta | X16: Reformada por el estudio de Luisa Olazábal. La más cara de las que publican precio. | Y16: 4.5 | Z16: 1203 | AA16: 4,9 (213) | AB16: +34 913 57 32 55 | AC16: https://www.bodas.net/fincas/la-casa-de-monico--e2021 | AD16: =HYPERLINK("https://www.google.com/maps/search/?api=1&query="&AE16&","&AF16,"Abrir mapa") -> Abrir mapa | AE16: 40.465202 | AF16: -3.780812 | AG16: =ROUND(F16*Notas!$B$8/Notas!$B$9*60,0) -> 19 | AH16: =HYPERLINK("https://www.google.com/maps/dir/?api=1&origin=Calle+de+Ayala+71,+Madrid&destination="&AE16&","&AF16&"&travelmode=driving","Ver ruta y tiempo") -> Ver ruta y tiempo | AJ16: =IF(AI16="",HYPERLINK("https://www.google.com/search?q=site%3Ainstagram.com+La+Casa+de+M%C3%B3nico+bodas","Buscar en Instagram"),HYPERLINK("https://instagram.com/"&SUBSTITUTE(AI16,"@",""),AI16)) -> Buscar en Instagram
A17: 16 | B17: Finca La Gaivota | C17: Finca con casa señorial (años 40) | D17: Madrid – Aravaca | E17: C/ Ardales s/n, 28023 Madrid | F17: =ROUND(6371*2*ASIN(SQRT(SIN(RADIANS(AE17-Notas!$B$4)/2)^2+COS(RADIANS(Notas!$B$4))*COS(RADIANS(AE17))*SIN(RADIANS(AF17-Notas!$B$5)/2)^2)),1) -> 9.8 | G17: =IF(F17<=Notas!$B$6,"Sí","No") -> Sí | H17: No publicado (pedir presupuesto) | J17: =IF(ISNUMBER(I17),I17*Notas!$B$7,"") | L17: 500 | M17: Hasta ~500 (prensa); pradera >1.000 m² para banquetes | N17: Isabel Maestre Catering | O17: No (catering asociado) – confirmar | P17: Casa señorial + carpa-invernadero acristalado + pradera + piscina; ~10.000 m² de jardines de Fernando Caruncho | Q17: Varios | R17: Sí (jardines, pradera y terraza) | S17: No consta – preguntar | T17: Sí (jardín) | U17: No | V17: No consta | W17: No consta | X17: A 8 min del centro. Invernadero como plan B si llueve. | Y17: 4.4 | Z17: 193 | AA17: — | AB17: +34 650 85 13 10 | AC17: https://www.salir.com/finca-la-gaivota-madrid-neg-141910.html | AD17: =HYPERLINK("https://www.google.com/maps/search/?api=1&query="&AE17&","&AF17,"Abrir mapa") -> Abrir mapa | AE17: 40.461983 | AF17: -3.7827754 | AG17: =ROUND(F17*Notas!$B$8/Notas!$B$9*60,0) -> 19 | AH17: =HYPERLINK("https://www.google.com/maps/dir/?api=1&origin=Calle+de+Ayala+71,+Madrid&destination="&AE17&","&AF17&"&travelmode=driving","Ver ruta y tiempo") -> Ver ruta y tiempo | AJ17: =IF(AI17="",HYPERLINK("https://www.google.com/search?q=site%3Ainstagram.com+Finca+La+Gaivota+bodas","Buscar en Instagram"),HYPERLINK("https://instagram.com/"&SUBSTITUTE(AI17,"@",""),AI17)) -> Buscar en Instagram
A18: 17 | B18: Finca Astilbe (by Eneldo) | C18: Finca de 40.000 m² | D18: Madrid – Fuencarral | E18: Carr. de Fuencarral km 1,9, 28049 Madrid | F18: =ROUND(6371*2*ASIN(SQRT(SIN(RADIANS(AE18-Notas!$B$4)/2)^2+COS(RADIANS(Notas!$B$4))*COS(RADIANS(AE18))*SIN(RADIANS(AF18-Notas!$B$5)/2)^2)),1) -> 10.6 | G18: =IF(F18<=Notas!$B$6,"Sí","No") -> Sí | H18: Menú desde 145 €/invitado | I18: 145 | J18: =IF(ISNUMBER(I18),I18*Notas!$B$7,"") -> 17400 | K18: 150 | L18: 600 | M18: 150–600 | N18: Eneldo Catering | O18: No (catering de la casa); tarta propia sin recargo | P18: Salones Plenaria (650 banquete), Columnas (190), Dos Aguas (160), porche (140) y jardín 2.220 m² (640); zona de fiesta con barra | Q18: Varios | R18: Sí (porche 175 m² + jardines) | S18: Sí – casita para que se cambien los novios | T18: Sí (zona de ceremonia) | U18: No | V18: Sí | W18: Cierran barra a la hora pactada | X18: Algunas reseñas se quejan del camino de acceso (baches) y de una cancelación por doble reserva: dejarlo todo por escrito. | Y18: 4 | Z18: 656 | AA18: 4,9 (19) | AB18: +34 917 37 65 25 | AC18: https://www.bodas.net/fincas/finca-astilbe--e218138 | AD18: =HYPERLINK("https://www.google.com/maps/search/?api=1&query="&AE18&","&AF18,"Abrir mapa") -> Abrir mapa | AE18: 40.522903 | AF18: -3.6670449 | AG18: =ROUND(F18*Notas!$B$8/Notas!$B$9*60,0) -> 21 | AH18: =HYPERLINK("https://www.google.com/maps/dir/?api=1&origin=Calle+de+Ayala+71,+Madrid&destination="&AE18&","&AF18&"&travelmode=driving","Ver ruta y tiempo") -> Ver ruta y tiempo | AJ18: =IF(AI18="",HYPERLINK("https://www.google.com/search?q=site%3Ainstagram.com+Finca+Astilbe++by+Eneldo+bodas","Buscar en Instagram"),HYPERLINK("https://instagram.com/"&SUBSTITUTE(AI18,"@",""),AI18)) -> Buscar en Instagram
A19: 18 | B19: El Mirador de Cuatrovientos (incl. Finca Las Palmeras) | C19: Complejo de fincas con jardines | D19: Madrid – Latina (Cuatro Vientos) | E19: Ctra. Barrio de la Fortuna 14, 28054 Madrid | F19: =ROUND(6371*2*ASIN(SQRT(SIN(RADIANS(AE19-Notas!$B$4)/2)^2+COS(RADIANS(Notas!$B$4))*COS(RADIANS(AE19))*SIN(RADIANS(AF19-Notas!$B$5)/2)^2)),1) -> 10.8 | G19: =IF(F19<=Notas!$B$6,"Sí","No") -> Sí | H19: Menú desde 99 €/invitado | I19: 99 | J19: =IF(ISNUMBER(I19),I19*Notas!$B$7,"") -> 11880 | K19: 40 | L19: 1000 | M19: 40–1.000 | N19: Cocina propia | O19: No (catering de la casa) | P19: Varios espacios/fincas (p. ej. Finca Las Palmeras) con jardines, chill out y salones | Q19: Varios | R19: Sí (jardines, chill out, balinesas) | S19: No consta – preguntar | T19: Sí | U19: No | V19: Sí | W19: No consta | X19: De las más valoradas de Madrid en bodas.net (786 opiniones, Wedding Awards). | Y19: 4.3 | Z19: 4028 | AA19: 4,9 (786) | AB19: +34 915 08 54 45 | AC19: https://www.bodas.net/fincas/el-mirador-de-cuatrovientos--e3257 | AD19: =HYPERLINK("https://www.google.com/maps/search/?api=1&query="&AE19&","&AF19,"Abrir mapa") -> Abrir mapa | AE19: 40.365442 | AF19: -3.7736647 | AG19: =ROUND(F19*Notas!$B$8/Notas!$B$9*60,0) -> 21 | AH19: =HYPERLINK("https://www.google.com/maps/dir/?api=1&origin=Calle+de+Ayala+71,+Madrid&destination="&AE19&","&AF19&"&travelmode=driving","Ver ruta y tiempo") -> Ver ruta y tiempo | AJ19: =IF(AI19="",HYPERLINK("https://www.google.com/search?q=site%3Ainstagram.com+El+Mirador+de+Cuatrovientos++incl.+Finca+Las+Palmeras+bodas","Buscar en Instagram"),HYPERLINK("https://instagram.com/"&SUBSTITUTE(AI19,"@",""),AI19)) -> Buscar en Instagram
A20: 19 | B20: U-Zalacaín La Finca | C20: Finca con jardines | D20: Pozuelo de Alarcón (urb. La Finca) | E20: P.º Club Deportivo 4, Urb. La Finca, 28223 Pozuelo de Alarcón | F20: =ROUND(6371*2*ASIN(SQRT(SIN(RADIANS(AE20-Notas!$B$4)/2)^2+COS(RADIANS(Notas!$B$4))*COS(RADIANS(AE20))*SIN(RADIANS(AF20-Notas!$B$5)/2)^2)),1) -> 10.9 | G20: =IF(F20<=Notas!$B$6,"Sí","No") -> Sí | H20: Menú desde 135 €/invitado | I20: 135 | J20: =IF(ISNUMBER(I20),I20*Notas!$B$7,"") -> 16200 | L20: 450 | M20: Hasta 450 | N20: UZalacaín Catering & Eventos | O20: No (catering de la casa) | P20: Jardines para ceremonia, cóctel y cena al aire libre + salón interior | Q20: Varios | R20: Sí (jardines) | S20: No consta – preguntar | T20: Sí | U20: No | V20: No consta | W20: No consta | X20: 5% de descuento para novios de bodas.net. | Y20: 4.5 | Z20: 641 | AA20: 5,0 (40) | AB20: +34 917 99 71 90 | AC20: https://www.bodas.net/fincas/u-zalacain-la-finca--e176648 | AD20: =HYPERLINK("https://www.google.com/maps/search/?api=1&query="&AE20&","&AF20,"Abrir mapa") -> Abrir mapa | AE20: 40.419334 | AF20: -3.8038793 | AG20: =ROUND(F20*Notas!$B$8/Notas!$B$9*60,0) -> 21 | AH20: =HYPERLINK("https://www.google.com/maps/dir/?api=1&origin=Calle+de+Ayala+71,+Madrid&destination="&AE20&","&AF20&"&travelmode=driving","Ver ruta y tiempo") -> Ver ruta y tiempo | AJ20: =IF(AI20="",HYPERLINK("https://www.google.com/search?q=site%3Ainstagram.com+U-Zalaca%C3%ADn+La+Finca+bodas","Buscar en Instagram"),HYPERLINK("https://instagram.com/"&SUBSTITUTE(AI20,"@",""),AI20)) -> Buscar en Instagram
A21: 20 | B21: Finca La Muñoza (La Cococha) | C21: Finca con palacio neoclásico | D21: Madrid – El Pardo (entrada) | E21: Ctra. de El Pardo a Fuencarral km 4,1, 28049 Madrid | F21: =ROUND(6371*2*ASIN(SQRT(SIN(RADIANS(AE21-Notas!$B$4)/2)^2+COS(RADIANS(Notas!$B$4))*COS(RADIANS(AE21))*SIN(RADIANS(AF21-Notas!$B$5)/2)^2)),1) -> 11 | G21: =IF(F21<=Notas!$B$6,"Sí","No") -> Sí | H21: Menú desde 125 €/invitado | I21: 125 | J21: =IF(ISNUMBER(I21),I21*Notas!$B$7,"") -> 15000 | K21: 100 | L21: 600 | M21: 100–600 | N21: Catering La Cococha | O21: No – exclusivo | P21: Palacio con salones + carpa + 28.000 m² de jardines paisajistas | Q21: Varios | R21: Sí (jardines y carpa) | S21: No consta – preguntar | T21: Sí (jardines) | U21: No | V21: No consta | W21: No consta | X21: Palacio habitado por la reina María Cristina de Borbón. Wedding Awards 2022. En Google aparece como «La Quinta Muñoza». | Y21: 4.5 | Z21: 510 | AA21: 5,0 (23) | AB21: +34 913 76 16 77 | AC21: https://www.bodas.net/fincas/finca-la-munoza-la-cococha--e173003 | AD21: =HYPERLINK("https://www.google.com/maps/search/?api=1&query="&AE21&","&AF21,"Abrir mapa") -> Abrir mapa | AE21: 40.514175 | AF21: -3.7388168 | AG21: =ROUND(F21*Notas!$B$8/Notas!$B$9*60,0) -> 21 | AH21: =HYPERLINK("https://www.google.com/maps/dir/?api=1&origin=Calle+de+Ayala+71,+Madrid&destination="&AE21&","&AF21&"&travelmode=driving","Ver ruta y tiempo") -> Ver ruta y tiempo | AJ21: =IF(AI21="",HYPERLINK("https://www.google.com/search?q=site%3Ainstagram.com+Finca+La+Mu%C3%B1oza++La+Cococha+bodas","Buscar en Instagram"),HYPERLINK("https://instagram.com/"&SUBSTITUTE(AI21,"@",""),AI21)) -> Buscar en Instagram
A22: 21 | B22: Real Club La Moraleja | C22: Club de golf | D22: Alcobendas (La Moraleja) | E22: P.º Marquesa Viuda de Aldama 50, 28109 Alcobendas | F22: =ROUND(6371*2*ASIN(SQRT(SIN(RADIANS(AE22-Notas!$B$4)/2)^2+COS(RADIANS(Notas!$B$4))*COS(RADIANS(AE22))*SIN(RADIANS(AF22-Notas!$B$5)/2)^2)),1) -> 11.2 | G22: =IF(F22<=Notas!$B$6,"Sí","No") -> Sí | H22: No publicado (media de fincas en Alcobendas en bodas.net ≈150 €/invitado) | J22: =IF(ISNUMBER(I22),I22*Notas!$B$7,"") | M22: No publicado | N22: Cocinas propias del club («no somos catering») | O22: No (cocina propia del club) | P22: Casa club con salones + exteriores/campo de golf (si llueve, todo se monta dentro) | Q22: Varios | R22: Sí (exteriores) | S22: No consta – preguntar | T22: Consultar | U22: No | V22: Sí | W22: No consta | X22: Wedding Awards 2025 en bodas.net; larga trayectoria en bodas. Club privado: preguntar condiciones para no socios. Una reseña de Google lo ve algo anticuado para >200 personas. | Y22: 4.4 | Z22: 1022 | AA22: 4,9 (51) | AB22: +34 916 50 07 00 | AC22: https://www.bodas.net/fincas/real-club-la-moraleja--e81710 | AD22: =HYPERLINK("https://www.google.com/maps/search/?api=1&query="&AE22&","&AF22,"Abrir mapa") -> Abrir mapa | AE22: 40.517321 | AF22: -3.6171963 | AG22: =ROUND(F22*Notas!$B$8/Notas!$B$9*60,0) -> 22 | AH22: =HYPERLINK("https://www.google.com/maps/dir/?api=1&origin=Calle+de+Ayala+71,+Madrid&destination="&AE22&","&AF22&"&travelmode=driving","Ver ruta y tiempo") -> Ver ruta y tiempo | AJ22: =IF(AI22="",HYPERLINK("https://www.google.com/search?q=site%3Ainstagram.com+Real+Club+La+Moraleja+bodas","Buscar en Instagram"),HYPERLINK("https://instagram.com/"&SUBSTITUTE(AI22,"@",""),AI22)) -> Buscar en Instagram
A23: 22 | B23: Finca Petit Moraleja | C23: Finca para eventos | D23: Alcobendas | E23: Vereda de las Peñas 29, 28109 Alcobendas | F23: =ROUND(6371*2*ASIN(SQRT(SIN(RADIANS(AE23-Notas!$B$4)/2)^2+COS(RADIANS(Notas!$B$4))*COS(RADIANS(AE23))*SIN(RADIANS(AF23-Notas!$B$5)/2)^2)),1) -> 12.5 | G23: =IF(F23<=Notas!$B$6,"Sí","No") -> Sí | H23: No publicado | J23: =IF(ISNUMBER(I23),I23*Notas!$B$7,"") | M23: No publicado | N23: No consta | O23: Consultar | P23: No consta | Q23: Consultar | R23: Consultar | S23: No consta – preguntar | T23: Consultar | U23: No | V23: No consta | W23: No consta | X23: Muy pocas reseñas; información pública escasa. | Y23: 4.3 | Z23: 4 | AA23: — | AB23: +34 915 65 53 75 | AC23: Google Maps | AD23: =HYPERLINK("https://www.google.com/maps/search/?api=1&query="&AE23&","&AF23,"Abrir mapa") -> Abrir mapa | AE23: 40.530434 | AF23: -3.6171501 | AG23: =ROUND(F23*Notas!$B$8/Notas!$B$9*60,0) -> 24 | AH23: =HYPERLINK("https://www.google.com/maps/dir/?api=1&origin=Calle+de+Ayala+71,+Madrid&destination="&AE23&","&AF23&"&travelmode=driving","Ver ruta y tiempo") -> Ver ruta y tiempo | AJ23: =IF(AI23="",HYPERLINK("https://www.google.com/search?q=site%3Ainstagram.com+Finca+Petit+Moraleja+bodas","Buscar en Instagram"),HYPERLINK("https://instagram.com/"&SUBSTITUTE(AI23,"@",""),AI23)) -> Buscar en Instagram
A24: 23 | B24: El Jardín de la Florida | C24: Casa con jardín para eventos | D24: Madrid – Aravaca (La Florida) | E24: C/ de Zarauz 2, 28023 Madrid | F24: =ROUND(6371*2*ASIN(SQRT(SIN(RADIANS(AE24-Notas!$B$4)/2)^2+COS(RADIANS(Notas!$B$4))*COS(RADIANS(AE24))*SIN(RADIANS(AF24-Notas!$B$5)/2)^2)),1) -> 12.6 | G24: =IF(F24<=Notas!$B$6,"Sí","No") -> Sí | H24: No publicado | J24: =IF(ISNUMBER(I24),I24*Notas!$B$7,"") | M24: No publicado (formato pequeño) | N24: Las opiniones sugieren que se contrata catering aparte | O24: Posiblemente sí – confirmar | P24: Casa + jardín con piscina y pista de tenis | Q24: Consultar | R24: Sí (jardín) | S24: Casa disponible – preguntar | T24: Consultar | U24: No | V24: No consta | W24: No consta | X24: Pocas reseñas (8). Interesante si buscáis traer vuestro propio catering. | Y24: 4.9 | Z24: 8 | AA24: — | AB24: +34 606 33 16 40 | AC24: Google Maps (ficha y opiniones) | AD24: =HYPERLINK("https://www.google.com/maps/search/?api=1&query="&AE24&","&AF24,"Abrir mapa") -> Abrir mapa | AE24: 40.469351 | AF24: -3.8145161 | AG24: =ROUND(F24*Notas!$B$8/Notas!$B$9*60,0) -> 25 | AH24: =HYPERLINK("https://www.google.com/maps/dir/?api=1&origin=Calle+de+Ayala+71,+Madrid&destination="&AE24&","&AF24&"&travelmode=driving","Ver ruta y tiempo") -> Ver ruta y tiempo | AJ24: =IF(AI24="",HYPERLINK("https://www.google.com/search?q=site%3Ainstagram.com+El+Jard%C3%ADn+de+la+Florida+bodas","Buscar en Instagram"),HYPERLINK("https://instagram.com/"&SUBSTITUTE(AI24,"@",""),AI24)) -> Buscar en Instagram
A25: 24 | B25: Initium (Artigot Catering) | C25: Finca nueva y reformada | D25: Madrid – Fuencarral (Cantoblanco) | E25: Carr. de Canto Blanco 14, 28049 Madrid | F25: =ROUND(6371*2*ASIN(SQRT(SIN(RADIANS(AE25-Notas!$B$4)/2)^2+COS(RADIANS(Notas!$B$4))*COS(RADIANS(AE25))*SIN(RADIANS(AF25-Notas!$B$5)/2)^2)),1) -> 12.9 | G25: =IF(F25<=Notas!$B$6,"Sí","No") -> Sí | H25: Menú desde 150 €/invitado | I25: 150 | J25: =IF(ISNUMBER(I25),I25*Notas!$B$7,"") -> 18000 | K25: 75 | L25: 270 | M25: 75–270 | N25: Artigot Catering | O25: No (catering de la casa) | P25: Salón + carpa (ceremonia) + zona de fuentes para el cóctel | Q25: Varios | R25: Sí (jardín y fuentes) | S25: No consta – preguntar | T25: Sí (en carpa) | U25: No | V25: No consta | W25: No consta | X25: Una reseña de 2026 menciona fallos de coordinación a la llegada (verja cerrada). | Y25: 4.7 | Z25: 50 | AA25: 4,9 (19) | AB25: +34 663 25 18 33 | AC25: https://www.bodas.net/fincas/initium-artigot-catering--e258289 | AD25: =HYPERLINK("https://www.google.com/maps/search/?api=1&query="&AE25&","&AF25,"Abrir mapa") -> Abrir mapa | AE25: 40.543754 | AF25: -3.6831698 | AG25: =ROUND(F25*Notas!$B$8/Notas!$B$9*60,0) -> 25 | AH25: =HYPERLINK("https://www.google.com/maps/dir/?api=1&origin=Calle+de+Ayala+71,+Madrid&destination="&AE25&","&AF25&"&travelmode=driving","Ver ruta y tiempo") -> Ver ruta y tiempo | AJ25: =IF(AI25="",HYPERLINK("https://www.google.com/search?q=site%3Ainstagram.com+Initium++Artigot+Catering+bodas","Buscar en Instagram"),HYPERLINK("https://instagram.com/"&SUBSTITUTE(AI25,"@",""),AI25)) -> Buscar en Instagram
A26: 25 | B26: Finca El Chaparral | C26: Residencia del s. XIX rehabilitada con jardines (Marqués de Mondéjar) | D26: Madrid – Aravaca / Pozuelo | E26: Finca La Escorzonera s/n, 28023 Madrid | F26: =ROUND(6371*2*ASIN(SQRT(SIN(RADIANS(AE26-Notas!$B$4)/2)^2+COS(RADIANS(Notas!$B$4))*COS(RADIANS(AE26))*SIN(RADIANS(AF26-Notas!$B$5)/2)^2)),1) -> 13 | G26: =IF(F26<=Notas!$B$6,"Sí","No") -> Sí | H26: No publicado | J26: =IF(ISNUMBER(I26),I26*Notas!$B$7,"") | M26: No publicado (exigen un mínimo de invitados) | N26: No consta (reseñas: catering impecable) | O26: Consultar | P26: Gran finca con jardines | Q26: Consultar | R26: Sí (jardines) | S26: No consta – preguntar | T26: Consultar | U26: No | V26: No consta | W26: Fiesta hasta ~02:00 (según opiniones) | X26: Exclusiva y elegante; algunas reseñas critican el trato comercial. En la misma finca (La Escorzonera) está Torzares, que figura en bodas.net con catering aparte. | Y26: 4.6 | Z26: 267 | AA26: — | AB26: +34 914 41 55 44 | AC26: Google Maps (ficha y opiniones) | AD26: =HYPERLINK("https://www.google.com/maps/search/?api=1&query="&AE26&","&AF26,"Abrir mapa") -> Abrir mapa | AE26: 40.468266 | AF26: -3.8202418 | AG26: =ROUND(F26*Notas!$B$8/Notas!$B$9*60,0) -> 25 | AH26: =HYPERLINK("https://www.google.com/maps/dir/?api=1&origin=Calle+de+Ayala+71,+Madrid&destination="&AE26&","&AF26&"&travelmode=driving","Ver ruta y tiempo") -> Ver ruta y tiempo | AJ26: =IF(AI26="",HYPERLINK("https://www.google.com/search?q=site%3Ainstagram.com+Finca+El+Chaparral+bodas","Buscar en Instagram"),HYPERLINK("https://instagram.com/"&SUBSTITUTE(AI26,"@",""),AI26)) -> Buscar en Instagram
A27: 26 | B27: Torzares (finca La Escorzonera) | C27: Casa/finca de alquiler para eventos | D27: Pozuelo de Alarcón / Aravaca (La Escorzonera) | E27: Finca La Escorzonera, Pozuelo de Alarcón (coordenadas aproximadas de la finca) | F27: =ROUND(6371*2*ASIN(SQRT(SIN(RADIANS(AE27-Notas!$B$4)/2)^2+COS(RADIANS(Notas!$B$4))*COS(RADIANS(AE27))*SIN(RADIANS(AF27-Notas!$B$5)/2)^2)),1) -> 13.6 | G27: =IF(F27<=Notas!$B$6,"Sí","No") -> Sí | H27: Alquiler de la finca con coste fijo (no publicado) + catering aparte | J27: =IF(ISNUMBER(I27),I27*Notas!$B$7,"") | K27: 150 | L27: 400 | M27: 150–400 | N27: Se contrata empresa de catering (la tarta, p. ej., «se habla con la empresa de catering seleccionada») | O27: Probablemente sí (catering aparte) – confirmar si hay lista | P27: Espacios amplios y versátiles + jardines y terrazas; ofrecen también decoración | Q27: Varios | R27: Sí (jardines y terrazas) | S27: Es una vivienda: preguntar por habitaciones para vestirse | T27: Consultar | U27: Consultar | V27: No consta | W27: No consta | X27: Sin recargo por mínimo: el alquiler es un coste fijo. Está en la misma finca (La Escorzonera) que Finca El Chaparral: confirmar si comparten espacio. Media de fincas en Pozuelo en bodas.net ≈180 €/invitado. | AA27: — | AB27: — | AC27: https://www.bodas.net/fincas/torzares--e286605 | AD27: =HYPERLINK("https://www.google.com/maps/search/?api=1&query="&AE27&","&AF27,"Abrir mapa") -> Abrir mapa | AE27: 40.457402 | AF27: -3.8319845 | AG27: =ROUND(F27*Notas!$B$8/Notas!$B$9*60,0) -> 27 | AH27: =HYPERLINK("https://www.google.com/maps/dir/?api=1&origin=Calle+de+Ayala+71,+Madrid&destination="&AE27&","&AF27&"&travelmode=driving","Ver ruta y tiempo") -> Ver ruta y tiempo | AJ27: =IF(AI27="",HYPERLINK("https://www.google.com/search?q=site%3Ainstagram.com+Torzares++finca+La+Escorzonera+bodas","Buscar en Instagram"),HYPERLINK("https://instagram.com/"&SUBSTITUTE(AI27,"@",""),AI27)) -> Buscar en Instagram
A28: 27 | B28: Restaurante San Francisco (El Pardo) | C28: Restaurante con jardín | D28: Madrid – El Pardo | E28: Pista del Cristo de El Pardo 3, 28048 Madrid | F28: =ROUND(6371*2*ASIN(SQRT(SIN(RADIANS(AE28-Notas!$B$4)/2)^2+COS(RADIANS(Notas!$B$4))*COS(RADIANS(AE28))*SIN(RADIANS(AF28-Notas!$B$5)/2)^2)),1) -> 13.6 | G28: =IF(F28<=Notas!$B$6,"Sí","No") -> Sí | H28: No publicado | J28: =IF(ISNUMBER(I28),I28*Notas!$B$7,"") | M28: No publicado | N28: Cocina propia | O28: No (catering de la casa) | P28: Varios salones de banquetes de distintos tamaños + jardín arbolado | Q28: Varios | R28: Sí (jardín con árboles) | S28: No consta – preguntar | T28: Sí (jardín) | U28: No | V28: No consta | W28: No consta | X28: Bodas con servicio tipo buffet según opiniones. | Y28: 4.2 | Z28: 3133 | AA28: — | AB28: +34 913 76 07 52 | AC28: Google Maps (ficha y opiniones) | AD28: =HYPERLINK("https://www.google.com/maps/search/?api=1&query="&AE28&","&AF28,"Abrir mapa") -> Abrir mapa | AE28: 40.520118 | AF28: -3.7813086 | AG28: =ROUND(F28*Notas!$B$8/Notas!$B$9*60,0) -> 27 | AH28: =HYPERLINK("https://www.google.com/maps/dir/?api=1&origin=Calle+de+Ayala+71,+Madrid&destination="&AE28&","&AF28&"&travelmode=driving","Ver ruta y tiempo") -> Ver ruta y tiempo | AJ28: =IF(AI28="",HYPERLINK("https://www.google.com/search?q=site%3Ainstagram.com+Restaurante+San+Francisco++El+Pardo+bodas","Buscar en Instagram"),HYPERLINK("https://instagram.com/"&SUBSTITUTE(AI28,"@",""),AI28)) -> Buscar en Instagram
A29: 28 | B29: Palacio del Negralejo (Grupo Negralejo) | C29: Palacio s. XVIII con jardines | D29: Rivas-Vaciamadrid | E29: Carr. de Mejorada km 3, 28522 Rivas-Vaciamadrid | F29: =ROUND(6371*2*ASIN(SQRT(SIN(RADIANS(AE29-Notas!$B$4)/2)^2+COS(RADIANS(Notas!$B$4))*COS(RADIANS(AE29))*SIN(RADIANS(AF29-Notas!$B$5)/2)^2)),1) -> 13.6 | G29: =IF(F29<=Notas!$B$6,"Sí","No") -> Sí | H29: Menú desde 150 €/invitado (incl. cóctel, menú, bodega, 4 h barra libre, degustación) | I29: 150 | J29: =IF(ISNUMBER(I29),I29*Notas!$B$7,"") -> 18000 | K29: 70 | L29: 400 | M29: 70–400 por boda | N29: Cocina propia | O29: No (catering de la casa) | P29: Salones Rosaleda, Pérgola y Boxes (+ bodegas); 11 espacios en el complejo | Q29: Varios | R29: Sí (jardines y patios) | S29: No consta – preguntar | T29: Sí | U29: No | V29: Sí (3 aparcamientos) | W29: 8 h de servicio incluidas | X29: Ojo: el complejo puede acoger varios eventos a la vez en espacios separados. | Y29: 4.4 | Z29: 2240 | AA29: 4,8 (179) – Grupo Negralejo | AB29: +34 916 69 11 25 | AC29: https://www.bodas.net/fincas/grupo-negralejo--e2063 | AD29: =HYPERLINK("https://www.google.com/maps/search/?api=1&query="&AE29&","&AF29,"Abrir mapa") -> Abrir mapa | AE29: 40.405487 | AF29: -3.5180427 | AG29: =ROUND(F29*Notas!$B$8/Notas!$B$9*60,0) -> 27 | AH29: =HYPERLINK("https://www.google.com/maps/dir/?api=1&origin=Calle+de+Ayala+71,+Madrid&destination="&AE29&","&AF29&"&travelmode=driving","Ver ruta y tiempo") -> Ver ruta y tiempo | AJ29: =IF(AI29="",HYPERLINK("https://www.google.com/search?q=site%3Ainstagram.com+Palacio+del+Negralejo++Grupo+Negralejo+bodas","Buscar en Instagram"),HYPERLINK("https://instagram.com/"&SUBSTITUTE(AI29,"@",""),AI29)) -> Buscar en Instagram
A30: 29 | B30: Jardines del Negralejo (Grupo Negralejo) | C30: Antigua Posta Real con jardines | D30: Rivas-Vaciamadrid | E30: Carr. de Mejorada km 2,5, 28522 Rivas-Vaciamadrid | F30: =ROUND(6371*2*ASIN(SQRT(SIN(RADIANS(AE30-Notas!$B$4)/2)^2+COS(RADIANS(Notas!$B$4))*COS(RADIANS(AE30))*SIN(RADIANS(AF30-Notas!$B$5)/2)^2)),1) -> 13.7 | G30: =IF(F30<=Notas!$B$6,"Sí","No") -> Sí | H30: Menú desde 150 €/invitado (incl. cóctel, menú, bodega, 4 h barra libre) | I30: 150 | J30: =IF(ISNUMBER(I30),I30*Notas!$B$7,"") -> 18000 | K30: 70 | L30: 400 | M30: 70–400 | N30: Cocina propia | O30: No (catering de la casa) | P30: Salones Balconada, Pabellón, Conde Duque y Posta Real (+ Herradura y Corrala) | Q30: Varios | R30: Sí (jardines y corrala) | S30: No consta – preguntar | T30: Sí | U30: No | V30: Sí | W30: 7 h de servicio incluidas | X30: Mismo grupo que el Palacio. Wedding Awards 2026. | Y30: 4.3 | Z30: 158 | AA30: 4,8 (179) – Grupo Negralejo | AB30: +34 916 69 11 25 | AC30: https://www.bodas.net/fincas/grupo-negralejo--e2063 | AD30: =HYPERLINK("https://www.google.com/maps/search/?api=1&query="&AE30&","&AF30,"Abrir mapa") -> Abrir mapa | AE30: 40.408571 | AF30: -3.5162788 | AG30: =ROUND(F30*Notas!$B$8/Notas!$B$9*60,0) -> 27 | AH30: =HYPERLINK("https://www.google.com/maps/dir/?api=1&origin=Calle+de+Ayala+71,+Madrid&destination="&AE30&","&AF30&"&travelmode=driving","Ver ruta y tiempo") -> Ver ruta y tiempo | AJ30: =IF(AI30="",HYPERLINK("https://www.google.com/search?q=site%3Ainstagram.com+Jardines+del+Negralejo++Grupo+Negralejo+bodas","Buscar en Instagram"),HYPERLINK("https://instagram.com/"&SUBSTITUTE(AI30,"@",""),AI30)) -> Buscar en Instagram
A31: 30 | B31: Finca La Alquería | C31: Finca de recreo (1890) con pabellones | D31: Madrid – junto a A-5 (km 12,8) | E31: A-5 km 12,8, 28922 Madrid | F31: =ROUND(6371*2*ASIN(SQRT(SIN(RADIANS(AE31-Notas!$B$4)/2)^2+COS(RADIANS(Notas!$B$4))*COS(RADIANS(AE31))*SIN(RADIANS(AF31-Notas!$B$5)/2)^2)),1) -> 14.8 | G31: =IF(F31<=Notas!$B$6,"Sí","No") -> Sí | H31: Menú desde 100 €/invitado | I31: 100 | J31: =IF(ISNUMBER(I31),I31*Notas!$B$7,"") -> 12000 | K31: 90 | L31: 1200 | M31: 90–1.200 (mín. 100 en La Ermita; 125 en los demás pabellones) | N31: Cocina propia (todo se elabora en la finca) | O31: No – exclusivo | P31: Pabellones La Ermita, Almazara, Brezo y Ciprés (~430 en banquete cada uno) + jardines, fuentes y lago (23.000 m²) | Q31: Varios | R31: Sí (jardines, pabellón exterior) | S31: No consta – preguntar | T31: Sí (jardín / Casa Ermita) | U31: No | V31: Sí (privado y amplio) | W31: No consta | X31: Más de 70 años organizando eventos. | Y31: 4.4 | Z31: 1514 | AA31: 4,9 (236) | AB31: +34 916 21 01 06 | AC31: https://www.bodas.net/fincas/finca-la-alqueria--e2004 | AD31: =HYPERLINK("https://www.google.com/maps/search/?api=1&query="&AE31&","&AF31,"Abrir mapa") -> Abrir mapa | AE31: 40.355196 | AF31: -3.8230821 | AG31: =ROUND(F31*Notas!$B$8/Notas!$B$9*60,0) -> 29 | AH31: =HYPERLINK("https://www.google.com/maps/dir/?api=1&origin=Calle+de+Ayala+71,+Madrid&destination="&AE31&","&AF31&"&travelmode=driving","Ver ruta y tiempo") -> Ver ruta y tiempo | AJ31: =IF(AI31="",HYPERLINK("https://www.google.com/search?q=site%3Ainstagram.com+Finca+La+Alquer%C3%ADa+bodas","Buscar en Instagram"),HYPERLINK("https://instagram.com/"&SUBSTITUTE(AI31,"@",""),AI31)) -> Buscar en Instagram
A32: 31 | B32: Finca Las Jarillas | C32: Finca de recreo y caza con lago | D32: Madrid – El Goloso (M-607) | E32: M-607 km 19,9, 28049 Madrid | F32: =ROUND(6371*2*ASIN(SQRT(SIN(RADIANS(AE32-Notas!$B$4)/2)^2+COS(RADIANS(Notas!$B$4))*COS(RADIANS(AE32))*SIN(RADIANS(AF32-Notas!$B$5)/2)^2)),1) -> 16.4 | G32: =IF(F32<=Notas!$B$6,"Sí","No") -> Sí | H32: No publicado | J32: =IF(ISNUMBER(I32),I32*Notas!$B$7,"") | L32: 500 | M32: Hasta ~500 en interior | N32: Aldovea Catering (también se cita La Cococha en opiniones) | O32: Consultar (posible lista de caterings) | P32: 3 salones (uno tipo invernadero) + patio andaluz acristalado con fuente + invernadero inglés; jardines y lago | Q32: Varios | R32: Sí (jardines, lago, invernadero) | S32: No consta – preguntar | T32: Sí (jardines) | U32: No | V32: Sí, amplio (acceso justo para autobuses de 13 m) | W32: No consta | X32: ⚠ Confirmado en opiniones: una boda prevista para marzo de 2026 tuvo que cambiar de finca porque «por un problema con la finca» no se podían celebrar eventos; hay reseñas posteriores de bodas, pero conviene confirmar disponibilidad y licencia por escrito. | Y32: 4.4 | Z32: 422 | AA32: — | AB32: +34 913 10 20 00 | AC32: https://www.naboo.app/explorer/houses/finca-las-jarillas | AD32: =HYPERLINK("https://www.google.com/maps/search/?api=1&query="&AE32&","&AF32,"Abrir mapa") -> Abrir mapa | AE32: 40.573087 | AF32: -3.7082064 | AG32: =ROUND(F32*Notas!$B$8/Notas!$B$9*60,0) -> 32 | AH32: =HYPERLINK("https://www.google.com/maps/dir/?api=1&origin=Calle+de+Ayala+71,+Madrid&destination="&AE32&","&AF32&"&travelmode=driving","Ver ruta y tiempo") -> Ver ruta y tiempo | AJ32: =IF(AI32="",HYPERLINK("https://www.google.com/search?q=site%3Ainstagram.com+Finca+Las+Jarillas+bodas","Buscar en Instagram"),HYPERLINK("https://instagram.com/"&SUBSTITUTE(AI32,"@",""),AI32)) -> Buscar en Instagram
A33: 32 | B33: El Antiguo Convento de Boadilla del Monte | C33: Convento s. XVII / hotel boutique | D33: Boadilla del Monte | E33: C/ las Monjas s/n, 28660 Boadilla del Monte | F33: =ROUND(6371*2*ASIN(SQRT(SIN(RADIANS(AE33-Notas!$B$4)/2)^2+COS(RADIANS(Notas!$B$4))*COS(RADIANS(AE33))*SIN(RADIANS(AF33-Notas!$B$5)/2)^2)),1) -> 17 | G33: =IF(F33<=Notas!$B$6,"Sí","No") -> Sí | H33: Menú desde 145 €/invitado | I33: 145 | J33: =IF(ISNUMBER(I33),I33*Notas!$B$7,"") -> 17400 | K33: 50 | L33: 500 | M33: 50–500 | N33: Cocina propia | O33: No (catering de la casa) | P33: Claustro, patio, jardín de gala y salones | Q33: Varios | R33: Sí (jardín de gala y patio) | S33: Sí – habitaciones del hotel | T33: Sí (patio/jardín) | U33: Sí (hotel) | V33: Sí | W33: No consta | X33: Convento fundado en 1674. | Y33: 4.5 | Z33: 1347 | AA33: 4,8 (297) | AB33: +34 916 32 22 20 | AC33: https://www.bodas.net/fincas/el-antiguo-convento-de-boadilla-del-monte--e1942 | AD33: =HYPERLINK("https://www.google.com/maps/search/?api=1&query="&AE33&","&AF33,"Abrir mapa") -> Abrir mapa | AE33: 40.407521 | AF33: -3.8755292 | AG33: =ROUND(F33*Notas!$B$8/Notas!$B$9*60,0) -> 33 | AH33: =HYPERLINK("https://www.google.com/maps/dir/?api=1&origin=Calle+de+Ayala+71,+Madrid&destination="&AE33&","&AF33&"&travelmode=driving","Ver ruta y tiempo") -> Ver ruta y tiempo | AJ33: =IF(AI33="",HYPERLINK("https://www.google.com/search?q=site%3Ainstagram.com+El+Antiguo+Convento+de+Boadilla+del+Monte+bodas","Buscar en Instagram"),HYPERLINK("https://instagram.com/"&SUBSTITUTE(AI33,"@",""),AI33)) -> Buscar en Instagram
A34: 33 | B34: Palacio de Aldovea | C34: Palacio-castillo con jardines (BIC) | D34: San Fernando de Henares / Torrejón | E34: Ctra. del Castillo 10, 28830 | F34: =ROUND(6371*2*ASIN(SQRT(SIN(RADIANS(AE34-Notas!$B$4)/2)^2+COS(RADIANS(Notas!$B$4))*COS(RADIANS(AE34))*SIN(RADIANS(AF34-Notas!$B$5)/2)^2)),1) -> 17.1 | G34: =IF(F34<=Notas!$B$6,"Sí","No") -> Sí | H34: No publicado | J34: =IF(ISNUMBER(I34),I34*Notas!$B$7,"") | K34: 30 | L34: 550 | M34: ~30 hasta 200–550 según espacio/fuente | N34: Históricamente Aldovea Catering (chef Rita Figueroa); hoy se citan varios caterings (Sazón, Santani, Gourmad, Espacio Catering) | O34: Consultar (posible lista cerrada) | P34: Palacio con varios salones + >2.000 m² de jardines | Q34: Varios | R34: Sí (jardines) | S34: No consta – preguntar | T34: Sí (jardines) | U34: No | V34: Sí | W34: 1 boda al día | X34: Castillo s. XI convertido en palacio s. XVIII; Bien de Interés Cultural. | Y34: 4.6 | Z34: 604 | AA34: — | AB34: +34 913 10 20 00 | AC34: https://www.hola.com/novias/20221231223804/espacios-boda-muchos-invitados-espana/ | AD34: =HYPERLINK("https://www.google.com/maps/search/?api=1&query="&AE34&","&AF34,"Abrir mapa") -> Abrir mapa | AE34: 40.432522 | AF34: -3.4737998 | AG34: =ROUND(F34*Notas!$B$8/Notas!$B$9*60,0) -> 33 | AH34: =HYPERLINK("https://www.google.com/maps/dir/?api=1&origin=Calle+de+Ayala+71,+Madrid&destination="&AE34&","&AF34&"&travelmode=driving","Ver ruta y tiempo") -> Ver ruta y tiempo | AJ34: =IF(AI34="",HYPERLINK("https://www.google.com/search?q=site%3Ainstagram.com+Palacio+de+Aldovea+bodas","Buscar en Instagram"),HYPERLINK("https://instagram.com/"&SUBSTITUTE(AI34,"@",""),AI34)) -> Buscar en Instagram
A35: 34 | B35: Finca Villa María | C35: Finca con palacete | D35: Las Rozas de Madrid | E35: Carr. de El Escorial km 0,1, 28231 Las Rozas | F35: =ROUND(6371*2*ASIN(SQRT(SIN(RADIANS(AE35-Notas!$B$4)/2)^2+COS(RADIANS(Notas!$B$4))*COS(RADIANS(AE35))*SIN(RADIANS(AF35-Notas!$B$5)/2)^2)),1) -> 17.2 | G35: =IF(F35<=Notas!$B$6,"Sí","No") -> Sí | H35: Menú desde 145 €/invitado (bodas.net); incluye 4 h de barra libre | I35: 145 | J35: =IF(ISNUMBER(I35),I35*Notas!$B$7,"") -> 17400 | M35: No publicado | N35: Propio (organizan bodas desde 1994) | O35: No (catering de la casa) – confirmar | P35: 2 espacios independientes en 10.000 m²: El Palacete (palacete s. XX, jardines, pabellón acristalado y discoteca en las antiguas cocheras) y La Casa del Cenador (cóctel, discoteca, jardín con cenador y terraza acristalada; ideal bodas pequeñas, p. ej. 65 invitados) | Q35: Varios | R35: Sí (jardín + terraza acristalada) | S35: No consta – preguntar | T35: Sí, al aire libre | U35: No | V35: Sí, privado | W35: 4 h de barra libre incluidas | X35: Más de 30 años organizando bodas; opiniones destacan a la coordinadora (Paz). | Y35: 4.3 | Z35: 441 | AA35: — | AB35: +34 630 93 25 82 | AC35: https://www.bodas.net/fincas/finca-villa-maria--e2079 | AD35: =HYPERLINK("https://www.google.com/maps/search/?api=1&query="&AE35&","&AF35,"Abrir mapa") -> Abrir mapa | AE35: 40.485671 | AF35: -3.8643703 | AG35: =ROUND(F35*Notas!$B$8/Notas!$B$9*60,0) -> 34 | AH35: =HYPERLINK("https://www.google.com/maps/dir/?api=1&origin=Calle+de+Ayala+71,+Madrid&destination="&AE35&","&AF35&"&travelmode=driving","Ver ruta y tiempo") -> Ver ruta y tiempo | AJ35: =IF(AI35="",HYPERLINK("https://www.google.com/search?q=site%3Ainstagram.com+Finca+Villa+Mar%C3%ADa+bodas","Buscar en Instagram"),HYPERLINK("https://instagram.com/"&SUBSTITUTE(AI35,"@",""),AI35)) -> Buscar en Instagram
A36: 35 | B36: Gasterea Finca Restaurante | C36: Finca-restaurante | D36: Boadilla del Monte | E36: P.º de Madrid 3, 28660 Boadilla del Monte | F36: =ROUND(6371*2*ASIN(SQRT(SIN(RADIANS(AE36-Notas!$B$4)/2)^2+COS(RADIANS(Notas!$B$4))*COS(RADIANS(AE36))*SIN(RADIANS(AF36-Notas!$B$5)/2)^2)),1) -> 17.2 | G36: =IF(F36<=Notas!$B$6,"Sí","No") -> Sí | H36: Menú de boda desde 120 €/invitado (bodas.net) | I36: 120 | J36: =IF(ISNUMBER(I36),I36*Notas!$B$7,"") -> 14400 | L36: 300 | M36: Hasta 300 | N36: Cocina propia | O36: No (catering de la casa) | P36: 3 salones luminosos con vistas a los jardines (se pueden reservar por separado) | Q36: Varios | R36: Sí (salones abiertos a jardines) | S36: No consta – preguntar | T36: Consultar | U36: No | V36: Sí (cercano) | W36: 4 h de barra libre (según opiniones) | X36: Más de 25 años (Boadilla Gastronómica); junto a la estación de Metro Ligero Ferial. | Y36: 4.2 | Z36: 1130 | AA36: — | AB36: +34 606 33 81 20 | AC36: https://www.bodas.net/bodas/banquetes/restaurantes/madrid/boadilla-del-monte | AD36: =HYPERLINK("https://www.google.com/maps/search/?api=1&query="&AE36&","&AF36,"Abrir mapa") -> Abrir mapa | AE36: 40.40264 | AF36: -3.876775 | AG36: =ROUND(F36*Notas!$B$8/Notas!$B$9*60,0) -> 34 | AH36: =HYPERLINK("https://www.google.com/maps/dir/?api=1&origin=Calle+de+Ayala+71,+Madrid&destination="&AE36&","&AF36&"&travelmode=driving","Ver ruta y tiempo") -> Ver ruta y tiempo | AJ36: =IF(AI36="",HYPERLINK("https://www.google.com/search?q=site%3Ainstagram.com+Gasterea+Finca+Restaurante+bodas","Buscar en Instagram"),HYPERLINK("https://instagram.com/"&SUBSTITUTE(AI36,"@",""),AI36)) -> Buscar en Instagram
A37: 36 | B37: Finca La Constancia | C37: Finca con salones y jardín | D37: San Sebastián de los Reyes | E37: Camino Viejo de Barajas 12, 28702 S. S. de los Reyes | F37: =ROUND(6371*2*ASIN(SQRT(SIN(RADIANS(AE37-Notas!$B$4)/2)^2+COS(RADIANS(Notas!$B$4))*COS(RADIANS(AE37))*SIN(RADIANS(AF37-Notas!$B$5)/2)^2)),1) -> 17.5 | G37: =IF(F37<=Notas!$B$6,"Sí","No") -> Sí | H37: Menú 50–150 €/invitado | I37: 50 | J37: =IF(ISNUMBER(I37),I37*Notas!$B$7,"") -> 6000 | K37: 20 | L37: 300 | M37: 20–300 | N37: Cocina propia (restaurante) | O37: No (catering de la casa) | P37: Salones interiores + gran jardín (piscina, zona infantil) | Q37: Varios | R37: Sí (jardín) | S37: No consta – preguntar | T37: Consultar | U37: No | V37: No consta | W37: No consta | X37: Muy enfocada a comuniones y bautizos; la más barata de la lista. | Y37: 4.1 | Z37: 256 | AA37: — | AB37: +34 672 34 50 62 | AC37: https://www.bodas.net/salones-de-boda/finca-la-constancia--e204294 | AD37: =HYPERLINK("https://www.google.com/maps/search/?api=1&query="&AE37&","&AF37,"Abrir mapa") -> Abrir mapa | AE37: 40.564861 | AF37: -3.5742723 | AG37: =ROUND(F37*Notas!$B$8/Notas!$B$9*60,0) -> 34 | AH37: =HYPERLINK("https://www.google.com/maps/dir/?api=1&origin=Calle+de+Ayala+71,+Madrid&destination="&AE37&","&AF37&"&travelmode=driving","Ver ruta y tiempo") -> Ver ruta y tiempo | AJ37: =IF(AI37="",HYPERLINK("https://www.google.com/search?q=site%3Ainstagram.com+Finca+La+Constancia+bodas","Buscar en Instagram"),HYPERLINK("https://instagram.com/"&SUBSTITUTE(AI37,"@",""),AI37)) -> Buscar en Instagram
A38: 37 | B38: Villa Laureana | C38: Finca de >50.000 m² | D38: San Sebastián de los Reyes (A-1 km 23) | E38: Ctra. de Burgos km 23,1, 28709 S. S. de los Reyes | F38: =ROUND(6371*2*ASIN(SQRT(SIN(RADIANS(AE38-Notas!$B$4)/2)^2+COS(RADIANS(Notas!$B$4))*COS(RADIANS(AE38))*SIN(RADIANS(AF38-Notas!$B$5)/2)^2)),1) -> 18.9 | G38: =IF(F38<=Notas!$B$6,"Sí","No") -> Sí | H38: Menú desde 120 €/invitado | I38: 120 | J38: =IF(ISNUMBER(I38),I38*Notas!$B$7,"") -> 14400 | K38: 50 | L38: 800 | M38: 50–800 | N38: Cocina propia | O38: No (catering de la casa) | P38: Varios salones (Aranjuez, Laureana, Almudaina…) + jardines | Q38: Varios | R38: Sí (terraza y zona ajardinada) | S38: No consta – preguntar | T38: Sí | U38: No | V38: Sí (amplio, con sombra) | W38: No consta | X38: 6 promociones en bodas.net. Mayoría de opiniones buenas, alguna reciente «agridulce». | Y38: 4.3 | Z38: 1082 | AA38: 4,7 (156) | AB38: +34 916 54 43 12 | AC38: https://www.bodas.net/fincas/villa-laureana--e122599 | AD38: =HYPERLINK("https://www.google.com/maps/search/?api=1&query="&AE38&","&AF38,"Abrir mapa") -> Abrir mapa | AE38: 40.582 | AF38: -3.5824827 | AG38: =ROUND(F38*Notas!$B$8/Notas!$B$9*60,0) -> 37 | AH38: =HYPERLINK("https://www.google.com/maps/dir/?api=1&origin=Calle+de+Ayala+71,+Madrid&destination="&AE38&","&AF38&"&travelmode=driving","Ver ruta y tiempo") -> Ver ruta y tiempo | AJ38: =IF(AI38="",HYPERLINK("https://www.google.com/search?q=site%3Ainstagram.com+Villa+Laureana+bodas","Buscar en Instagram"),HYPERLINK("https://instagram.com/"&SUBSTITUTE(AI38,"@",""),AI38)) -> Buscar en Instagram
A39: 38 | B39: Señorío de Ajuria | C39: Finca con jardines | D39: Fuenlabrada | E39: C/ Litio 1, 28946 Fuenlabrada | F39: =ROUND(6371*2*ASIN(SQRT(SIN(RADIANS(AE39-Notas!$B$4)/2)^2+COS(RADIANS(Notas!$B$4))*COS(RADIANS(AE39))*SIN(RADIANS(AF39-Notas!$B$5)/2)^2)),1) -> 19.2 | G39: =IF(F39<=Notas!$B$6,"Sí","No") -> Sí | H39: Menú desde 90 €/invitado | I39: 90 | J39: =IF(ISNUMBER(I39),I39*Notas!$B$7,"") -> 10800 | K39: 25 | L39: 300 | M39: 25–300 | N39: Cocina propia (empresa familiar) | O39: No (catering de la casa) | P39: Finca con jardines y salones | Q39: Consultar | R39: Sí (jardines) | S39: No consta – preguntar | T39: Sí | U39: No | V39: No consta | W39: No consta | X39: Muy bien valorada en bodas.net (398 opiniones) y de las más económicas. | Y39: 4 | Z39: 954 | AA39: 4,9 (398) | AB39: +34 615 33 23 23 | AC39: https://www.bodas.net/fincas/senorio-de-ajuria--e2026 | AD39: =HYPERLINK("https://www.google.com/maps/search/?api=1&query="&AE39&","&AF39,"Abrir mapa") -> Abrir mapa | AE39: 40.266582 | AF39: -3.7582488 | AG39: =ROUND(F39*Notas!$B$8/Notas!$B$9*60,0) -> 37 | AH39: =HYPERLINK("https://www.google.com/maps/dir/?api=1&origin=Calle+de+Ayala+71,+Madrid&destination="&AE39&","&AF39&"&travelmode=driving","Ver ruta y tiempo") -> Ver ruta y tiempo | AJ39: =IF(AI39="",HYPERLINK("https://www.google.com/search?q=site%3Ainstagram.com+Se%C3%B1or%C3%ADo+de+Ajuria+bodas","Buscar en Instagram"),HYPERLINK("https://instagram.com/"&SUBSTITUTE(AI39,"@",""),AI39)) -> Buscar en Instagram

Sheet Justo fuera 20-24 km
A1: Nº | B1: Nombre | C1: Tipo de espacio | D1: Zona / municipio | E1: Dirección | F1: Distancia en línea recta (km) | G1: Precio orientativo | H1: Aforo | I1: Catering | J1: Observaciones | K1: Google (nota) | L1: Google (nº reseñas) | M1: Teléfono | N1: Fuente | O1: Latitud | P1: Longitud
A2: 1 | B2: Castillo de Viñuelas (Life Gourmet Catering) | C2: Castillo en el Monte de Viñuelas | D2: Madrid / Tres Cantos (Monte de Viñuelas) | E2: Ctra. de Colmenar km 20,9 – Ctra. Castillo de Viñuelas 10 | F2: =ROUND(6371*2*ASIN(SQRT(SIN(RADIANS(O2-Notas!$B$4)/2)^2+COS(RADIANS(Notas!$B$4))*COS(RADIANS(O2))*SIN(RADIANS(P2-Notas!$B$5)/2)^2)),1) -> 20.2 | G2: No publicado | H2: Gran capacidad (no publicada) | I2: Life Gourmet / Ramón Freixa Catering (cocina propia en cada espacio; mismo grupo que Club de Tiro) | J2: Una reseña cuenta que el cenador de cristal ardió y se sustituyó por carpa: preguntar estado actual. | K2: 4.6 | L2: 808 | M2: +34 610 09 32 56 | N2: https://www.bodas.net/castillos/castillo-de-vinuelas-life-gourmet-catering--e184062 | O2: 40.60778 | P2: -3.6467885
A3: 2 | B3: Finca Villa Chica | C3: Finca ecuestre / eventos | D3: San Sebastián de los Reyes (M-111) | E3: Ctra. Paracuellos-Fuente el Saz M-111 km 15,2 | F3: =ROUND(6371*2*ASIN(SQRT(SIN(RADIANS(O3-Notas!$B$4)/2)^2+COS(RADIANS(Notas!$B$4))*COS(RADIANS(O3))*SIN(RADIANS(P3-Notas!$B$5)/2)^2)),1) -> 20.3 | G3: No publicado | H3: No publicado | I3: Ofrecen catering (consultar) | J3: Eventos y celebraciones; confirmar si hacen bodas. | K3: 5 | L3: 47 | M3: +34 636 35 23 49 | N3: Google Maps | O3: 40.587398 | P3: -3.5602369
A4: 3 | B4: Restaurante Finca Liana | C4: Restaurante en parque | D4: Móstoles | E4: Av. de Iker Casillas 1, 28935 Móstoles | F4: =ROUND(6371*2*ASIN(SQRT(SIN(RADIANS(O4-Notas!$B$4)/2)^2+COS(RADIANS(Notas!$B$4))*COS(RADIANS(O4))*SIN(RADIANS(P4-Notas!$B$5)/2)^2)),1) -> 20.4 | G4: No publicado | H4: No publicado | I4: Cocina propia | J4: Restaurante con zonas interior/exterior dentro del parque Finca Liana. | K4: 4.2 | L4: 3785 | M4: +34 916 13 37 22 | N4: Google Maps | O4: 40.323532 | P4: -3.8746407
A5: 4 | B5: Espacio Éboli (INbodas) | C5: Finca con carpa | D5: Pinto | E5: C/ Cardenal Cisneros s/n, 28320 Pinto | F5: =ROUND(6371*2*ASIN(SQRT(SIN(RADIANS(O5-Notas!$B$4)/2)^2+COS(RADIANS(Notas!$B$4))*COS(RADIANS(O5))*SIN(RADIANS(P5-Notas!$B$5)/2)^2)),1) -> 20.8 | G5: No publicado | H5: No publicado | I5: Gestión INbodas | J5: Carpa grande, terraza con barras, fuentes, discoteca y parking; junto a la A-4. | K5: 4.3 | L5: 319 | M5: +34 691 60 79 73 | N5: Google Maps | O5: 40.240771 | P5: -3.6887562
A6: 5 | B6: Finca Feligrés | C6: Finca | D6: Arganda del Rey | E6: Ctra. de Velilla km 1, 28500 Arganda del Rey | F6: =ROUND(6371*2*ASIN(SQRT(SIN(RADIANS(O6-Notas!$B$4)/2)^2+COS(RADIANS(Notas!$B$4))*COS(RADIANS(O6))*SIN(RADIANS(P6-Notas!$B$5)/2)^2)),1) -> 21 | G6: No publicado | H6: No publicado | I6: Propio | J6: Solo 1 evento al día. | K6: 4.5 | L6: 301 | M6: +34 918 75 72 27 | N6: https://www.bodas.net/bodas/banquetes/fincas/madrid/rivas-vaciamadrid | O6: 40.32631 | P6: -3.4668462
A7: 6 | B7: El Cortijo de Mónico | C7: Cortijo andaluz | D7: Majadahonda | E7: Ctra. Villanueva del Pardillo M-851 km 1,5, 28222 Majadahonda | F7: =ROUND(6371*2*ASIN(SQRT(SIN(RADIANS(O7-Notas!$B$4)/2)^2+COS(RADIANS(Notas!$B$4))*COS(RADIANS(O7))*SIN(RADIANS(P7-Notas!$B$5)/2)^2)),1) -> 21.1 | G7: No publicado (Grupo Mónico) | H7: Hasta 500 sentados / 750 cóctel | I7: Mónico Catering (exclusivo) | J7: Parking 200 plazas. | K7: 4.4 | L7: 556 | M7: +34 913 57 32 55 | N7: https://www.bodas.net/fincas/el-cortijo-de-monico--e8570 | O7: 40.491372 | P7: -3.9104744
A8: 7 | B8: Complejo Cervantes (Finca de Bodas Madrid) | C8: Finca con salones | D8: Loeches | E8: M-206 km 2,6, 28890 Loeches | F8: =ROUND(6371*2*ASIN(SQRT(SIN(RADIANS(O8-Notas!$B$4)/2)^2+COS(RADIANS(Notas!$B$4))*COS(RADIANS(O8))*SIN(RADIANS(P8-Notas!$B$5)/2)^2)),1) -> 21.4 | G8: No publicado | H8: ~250 (algo justo según una reseña) | I8: Propio | J8: Menús para celíacos (bodas.net). Opiniones mixtas sobre la comida. | K8: 4.2 | L8: 412 | M8: +34 636 96 07 02 | N8: https://www.bodas.net/fincas/complejo-cervantes--e3033 | O8: 40.406813 | P8: -3.4246814
A9: 8 | B9: La Quinta de Jarama | C9: Quinta con jardines | D9: San Sebastián de los Reyes (A-1 km 26) | E9: Ctra. de Burgos A-1 km 26 | F9: =ROUND(6371*2*ASIN(SQRT(SIN(RADIANS(O9-Notas!$B$4)/2)^2+COS(RADIANS(Notas!$B$4))*COS(RADIANS(O9))*SIN(RADIANS(P9-Notas!$B$5)/2)^2)),1) -> 21.5 | G9: No publicado | H9: No publicado | I9: Propio | J9: Muy valorada (bodas.net 4,8 con 247 opiniones). | K9: 4.6 | L9: 1859 | M9: +34 916 58 90 24 | N9: https://www.bodas.net/fincas/la-quinta-de-jarama--e2565 | O9: 40.606386 | P9: -3.5782461
A10: 9 | B10: Soto de Mozanaque | C10: Finca | D10: Algete (M-111 km 16) | E10: Ctra. Paracuellos-Fuente el Saz M-111 km 16, 28140 Algete | F10: =ROUND(6371*2*ASIN(SQRT(SIN(RADIANS(O10-Notas!$B$4)/2)^2+COS(RADIANS(Notas!$B$4))*COS(RADIANS(O10))*SIN(RADIANS(P10-Notas!$B$5)/2)^2)),1) -> 22 | G10: No publicado | H10: No publicado | I10: Trabaja con Eneldo Catering (entre otros) | J10: Gran jardín para cóctel. | K10: 4.7 | L10: 237 | M10: +34 916 28 12 07 | N10: Google Maps | O10: 40.607878 | P10: -3.5696973
A11: 10 | B11: Gaztelubide Las Rozas | C11: Finca-restaurante | D11: Las Rozas de Madrid | E11: Ctra. Las Rozas-El Escorial km 5 | F11: =ROUND(6371*2*ASIN(SQRT(SIN(RADIANS(O11-Notas!$B$4)/2)^2+COS(RADIANS(Notas!$B$4))*COS(RADIANS(O11))*SIN(RADIANS(P11-Notas!$B$5)/2)^2)),1) -> 22.2 | G11: No publicado | H11: No publicado | I11: Propio | J11: Aparece en bodas.net entre las fincas con alojamiento. | K11: 4.3 | L11: 3081 | M11: +34 916 37 22 02 | N11: https://www.bodas.net/fincas/gaztelubide-las-rozas--e2010 | O11: 40.508734 | P11: -3.9155392
A12: 11 | B12: Finca El Monje | C12: Finca rústica | D12: Boadilla del Monte (M-513 km 10,6) | E12: M-513 km 10,6, 28669 Boadilla del Monte | F12: =ROUND(6371*2*ASIN(SQRT(SIN(RADIANS(O12-Notas!$B$4)/2)^2+COS(RADIANS(Notas!$B$4))*COS(RADIANS(O12))*SIN(RADIANS(P12-Notas!$B$5)/2)^2)),1) -> 22.4 | G12: No publicado | H12: No publicado | I12: Catering de la finca | J12: Estilo rústico. | K12: 4.6 | L12: 58 | M12: +34 915 34 23 87 | N12: Google Maps | O12: 40.39717 | P12: -3.9373318
A13: 12 | B13: Hacienda Chapoo | C13: Hacienda-restaurante | D13: Majadahonda | E13: Vía de servicio A-6 / M-509 km 3,3, 28222 Majadahonda | F13: =ROUND(6371*2*ASIN(SQRT(SIN(RADIANS(O13-Notas!$B$4)/2)^2+COS(RADIANS(Notas!$B$4))*COS(RADIANS(O13))*SIN(RADIANS(P13-Notas!$B$5)/2)^2)),1) -> 22.9 | G13: No publicado | H13: No publicado | I13: Propio | J13: Menús veganos (bodas.net). | K13: 4.4 | L13: 1227 | M13: +34 654 38 46 01 | N13: https://www.bodas.net/fincas/hacienda-chapoo--e173041 | O13: 40.485652 | P13: -3.9358984
A14: 13 | B14: Real Club de Golf del Race (Ciudalcampo) | C14: Club de golf | D14: San Sebastián de los Reyes (Ciudalcampo, A-1 km 28) | E14: Av. de Guadalix s/n, Ctra. A-1 km 28,1, 28707 | F14: =ROUND(6371*2*ASIN(SQRT(SIN(RADIANS(O14-Notas!$B$4)/2)^2+COS(RADIANS(Notas!$B$4))*COS(RADIANS(O14))*SIN(RADIANS(P14-Notas!$B$5)/2)^2)),1) -> 23.2 | G14: Menú 89–110 €/invitado (bodas.net) | H14: 80–500 | I14: Del club (consultar exclusividad) | J14: Club privado de socios que abre sus instalaciones a bodas. | K14: 4.5 | L14: 251 | M14: +34 916 57 00 11 | N14: https://www.bodas.net/fincas/real-club-de-golf-del-race--e235872 | O14: 40.626365 | P14: -3.5929698

Sheet Otros espacios
A1: Nº | B1: Nombre | C1: Tipo de espacio | D1: Zona / municipio | E1: Dirección | F1: Distancia en línea recta (km) | G1: Precio orientativo | H1: Aforo | I1: Catering | J1: Observaciones | K1: Google (nota) | L1: Google (nº reseñas) | M1: Teléfono | N1: Fuente | O1: Latitud | P1: Longitud
A2: 1 | B2: ABC Espacio | C2: Edificio urbano con terraza (salón) | D2: Madrid – Salamanca (Serrano) | E2: Antigua sede de ABC, C/ Serrano (coordenadas aproximadas) | F2: =ROUND(6371*2*ASIN(SQRT(SIN(RADIANS(O2-Notas!$B$4)/2)^2+COS(RADIANS(Notas!$B$4))*COS(RADIANS(O2))*SIN(RADIANS(P2-Notas!$B$5)/2)^2)),1) -> 1 | G2: Menú desde 150 €/invitado | H2: 50–500 | I2: Consultar | J2: No es finca: bodas.net lo clasifica como salón (4,9 con 37 opiniones). Terraza iluminada. | M2: — | N2: https://www.bodas.net/salones-de-boda/abc-espacio--e171015 | O2: 40.432 | P2: -3.6866
A3: 2 | B3: Faunia (Sala La Hacienda y jardines) | C3: Parque temático con salones | D3: Madrid – Valdebernardo | E3: Av. de las Comunidades 28, 28032 Madrid | F3: =ROUND(6371*2*ASIN(SQRT(SIN(RADIANS(O3-Notas!$B$4)/2)^2+COS(RADIANS(Notas!$B$4))*COS(RADIANS(O3))*SIN(RADIANS(P3-Notas!$B$5)/2)^2)),1) -> 6.8 | G3: No publicado | H3: No publicado | I3: Restauración del parque | J3: Figura en bodas.net como finca, pero las reseñas recientes de Google (comuniones) son muy negativas. | K3: 2.8 | L3: 26 | M3: +34 911 54 74 82 | N3: https://www.bodas.net/fincas/faunia--e3103 | O3: 40.391422 | P3: -3.6107702
A4: 3 | B4: El Barril de la Moraleja | C4: Restaurante (marisquería) con terraza | D4: Alcobendas (La Moraleja) | E4: C/ de la Estafeta 4, 28109 Alcobendas | F4: =ROUND(6371*2*ASIN(SQRT(SIN(RADIANS(O4-Notas!$B$4)/2)^2+COS(RADIANS(Notas!$B$4))*COS(RADIANS(O4))*SIN(RADIANS(P4-Notas!$B$5)/2)^2)),1) -> 9.8 | G4: No publicado | H4: No publicado | I4: Cocina propia | J4: Restaurante con varios espacios rodeados de vegetación y amplia terraza; figura en bodas.net como lugar para banquetes. No es finca. | K4: 4.2 | L4: 1303 | M4: +34 916 50 95 86 | N4: https://www.bodas.net/bodas/banquetes/madrid/alcobendas | O4: 40.51437 | P4: -3.6534396
A5: 4 | B5: Restaurante Finca del Valle | C5: Restaurante con espacio para eventos | D5: Madrid – Barajas | E5: C/ Zaorejas s/n, 28042 Madrid | F5: =ROUND(6371*2*ASIN(SQRT(SIN(RADIANS(O5-Notas!$B$4)/2)^2+COS(RADIANS(Notas!$B$4))*COS(RADIANS(O5))*SIN(RADIANS(P5-Notas!$B$5)/2)^2)),1) -> 10.2 | G5: No publicado | H5: ~300 (según una reseña) | I5: Cocina propia | J5: Restaurante; una reseña indica que acoge bodas de hasta 300 personas. | K5: 4 | L5: 299 | M5: +34 674 69 32 97 | N5: Google Maps | O5: 40.449884 | P5: -3.5592259
A6: 5 | B6: La Industrial de la Blonda | C6: Nave industrial (estilo industrial-chic) | D6: Alcobendas | E6: Av. de Valdelaparra 33, 28108 Alcobendas | F6: =ROUND(6371*2*ASIN(SQRT(SIN(RADIANS(O6-Notas!$B$4)/2)^2+COS(RADIANS(Notas!$B$4))*COS(RADIANS(O6))*SIN(RADIANS(P6-Notas!$B$5)/2)^2)),1) -> 12.6 | G6: Menú desde 145 €/invitado | H6: 60–250 | I6: De la casa (mismo grupo que Finca Las Tenadas) | J6: No es finca; >400 m² adaptables, porche y terraza exterior, parking. | K6: 4 | L6: 4 | M6: +34 915 19 47 01 | N6: https://www.bodas.net/fincas/la-industrial-de-la-blonda--e266763 | O6: 40.539216 | P6: -3.6485195
A7: 6 | B7: Nobile's Restaurante | C7: Restaurante / salón de banquetes | D7: Mejorada del Campo | E7: Ctra. Mejorada-San Fernando km 0,65, 28840 Mejorada del Campo | F7: =ROUND(6371*2*ASIN(SQRT(SIN(RADIANS(O7-Notas!$B$4)/2)^2+COS(RADIANS(Notas!$B$4))*COS(RADIANS(O7))*SIN(RADIANS(P7-Notas!$B$5)/2)^2)),1) -> 14.7 | G7: No publicado | H7: No publicado | I7: Cocina propia | J7: Salón de celebraciones con discoteca; no es finca. | K7: 4.2 | L7: 412 | M7: +34 916 79 28 13 | N7: Google Maps | O7: 40.3979 | P7: -3.5070196

Sheet Notas
A1: Fincas de boda a ≤20 km de Calle de Ayala 71 (Madrid) – parámetros, resumen y notas
A3: Origen | B3: Calle de Ayala 71, 28001 Madrid
A4: Latitud origen | B4: 40.427611 | C4: Coordenadas de Google Maps para Ayala 71
A5: Longitud origen | B5: -3.6761136
A6: Radio (km) | B6: 20 | C6: Cámbialo y se recalcula la columna «¿Dentro del radio?»
A7: Nº de invitados para estimar el coste | B7: 120 | C7: Cámbialo y se recalcula el coste orientativo (120 = media de bodas.net en fincas de Madrid)
A8: Factor carretera / línea recta | B8: 1.3 | C8: Por carretera suele ser 1,2–1,4 veces la distancia en línea recta
A9: Velocidad media estimada (km/h) | B9: 40 | C9: Media realista Madrid (M-30/A-6/A-1 con algo de tráfico). Es una ESTIMACIÓN: el tiempo exacto sale en el enlace de Google Maps
A11: Resumen (se recalcula solo)
A12: Fincas en la lista principal | B12: =COUNTA('Fincas 20 km'!B2:B39) -> 38
A13: …de ellas dentro del radio indicado | B13: =COUNTIF('Fincas 20 km'!G2:G39,"Sí") -> 38
A14: Fincas con precio de menú publicado | B14: =COUNT('Fincas 20 km'!I2:I39) -> 25
A15: Precio «desde» más bajo (€/invitado) | B15: =MIN('Fincas 20 km'!I2:I39) -> 50
A16: Precio «desde» medio (€/invitado) | B16: =ROUND(AVERAGE('Fincas 20 km'!I2:I39),0) -> 123
A17: Precio «desde» más alto (€/invitado) | B17: =MAX('Fincas 20 km'!I2:I39) -> 185
A18: Coste medio orientativo del menú para el nº de invitados de B7 (€) | B18: =ROUND(AVERAGE('Fincas 20 km'!J2:J39),0) -> 14784
A19: Con catering propio o exclusivo | B19: =COUNTIF('Fincas 20 km'!O2:O39,"No*") -> 31
A20: Con catering libre o lista de caterings (verde) | B20: =COUNTIF('Fincas 20 km'!O2:O39,"Posib*")+COUNTIF('Fincas 20 km'!O2:O39,"Proba*")+COUNTIF('Fincas 20 km'!O2:O39,"Lista*")+COUNTIF('Fincas 20 km'!O2:O39,"Sí*") -> 3
A21: Catering a consultar (amarillo) | B21: =COUNTIF('Fincas 20 km'!O2:O39,"Consultar*") -> 4
A22: Con varios salones/espacios | B22: =COUNTIF('Fincas 20 km'!Q2:Q39,"Varios") -> 33
A23: Con alojamiento en la propia finca | B23: =COUNTIF('Fincas 20 km'!U2:U39,"Sí*") -> 4
A24: Con cuarto/casita/habitación de novios confirmado | B24: =COUNTIF('Fincas 20 km'!S2:S39,"Sí*") -> 5
A25: Fincas «justo fuera» (20–24 km) | B25: =COUNTA('Justo fuera 20-24 km'!B2:B14) -> 13
A26: Otros espacios ≤20 km que no son finca | B26: =COUNTA('Otros espacios'!B2:B7) -> 6
A28: Cómo se ha hecho
A29: • Radio en línea recta (fórmula de Haversine) desde Ayala 71; por carretera suele ser un 20–40 % más.
A30: • Fuentes: fichas y listados de bodas.net (precios «desde», aforos, catering), Google Maps (ubicación, nota, reseñas, teléfono), webs y dosieres de los propios espacios (p. ej. «Bodas 2026» del Club de Campo), fichas de esmadrid.com y naboo.app, y prensa (¡HOLA! Novias, Marie Claire, Time Out). Consultado en octubre de 2026; 2ª revisión el 25/10/2026.
A31: • «Precio menú desde» es el mínimo anunciado por invitado; sube en sábados de temporada alta y con extras, IVA y mínimos de invitados. El coste orientativo solo multiplica ese mínimo por el nº de invitados de B7.
A32: • «No consta – preguntar» = no hay dato público fiable. El cuarto de novios casi nunca se publica.
A33: • Alcance: fincas, quintas, palacios/castillos con jardín, clubes con jardines y fincas-restaurante que celebran bodas. Hoteles urbanos y salones sin jardín quedan fuera; los dudosos están en «Otros espacios».
A35: Leyenda (columna «¿Catering libre?»)
A36: • Rojo: catering propio o exclusivo. • Verde: catering aparte o lista de caterings. • Amarillo: hay que preguntarlo. • Celdas amarillas B6 y B7: parámetros editables.
A38: Preguntas para la visita (lo que casi nunca se publica)
A39: 1. ¿Hay cuarto o sala para que se vistan los novios? ¿Desde qué hora se puede usar?
A40: 2. ¿El catering es exclusivo? Si no, ¿hay lista cerrada o canon por traer catering externo?
A41: 3. ¿El precio por invitado incluye IVA, cóctel, barra libre (cuántas horas), recena, decoración, DJ y degustación?
... A47: 9. ¿Parking y acceso para autobuses? ¿Exclusividad de música, fotógrafo o flores?
